[{"path":"src/main/java/Addlist.java","fileType":"java","lines":[{"lineNumber":1,"author":{"gitId":"ChubbsBunns"},"content":"import java.util.InputMismatchException;","lastModifiedDate":"2023-01-19"},{"lineNumber":2,"author":{"gitId":"ChubbsBunns"},"content":"import java.util.Scanner;","lastModifiedDate":"2023-01-16"},{"lineNumber":3,"author":{"gitId":"ChubbsBunns"},"content":"","lastModifiedDate":"2023-01-16"},{"lineNumber":4,"author":{"gitId":"ChubbsBunns"},"content":"public class Addlist {","lastModifiedDate":"2023-01-16"},{"lineNumber":5,"author":{"gitId":"ChubbsBunns"},"content":"","lastModifiedDate":"2023-01-31"},{"lineNumber":6,"author":{"gitId":"ChubbsBunns"},"content":"    public void AddList(){","lastModifiedDate":"2023-01-16"},{"lineNumber":7,"author":{"gitId":"ChubbsBunns"},"content":"        Task[] ListOfThings \u003d new Task[100];","lastModifiedDate":"2023-01-16"},{"lineNumber":8,"author":{"gitId":"ChubbsBunns"},"content":"        Scanner newScanner \u003d new Scanner(System.in);","lastModifiedDate":"2023-01-16"},{"lineNumber":9,"author":{"gitId":"ChubbsBunns"},"content":"        OutputUI outPutUI \u003d new OutputUI();","lastModifiedDate":"2023-02-01"},{"lineNumber":10,"author":{"gitId":"ChubbsBunns"},"content":"        Marker marker \u003d new Marker();","lastModifiedDate":"2023-02-01"},{"lineNumber":11,"author":{"gitId":"ChubbsBunns"},"content":"        int index \u003d 0;","lastModifiedDate":"2023-01-16"},{"lineNumber":12,"author":{"gitId":"ChubbsBunns"},"content":"        while(true) {","lastModifiedDate":"2023-02-01"},{"lineNumber":13,"author":{"gitId":"ChubbsBunns"},"content":"            try {","lastModifiedDate":"2023-01-19"},{"lineNumber":14,"author":{"gitId":"ChubbsBunns"},"content":"                System.out.println(\"______________________________________________\");","lastModifiedDate":"2023-01-16"},{"lineNumber":15,"author":{"gitId":"ChubbsBunns"},"content":"                String input \u003d newScanner.next();","lastModifiedDate":"2023-01-16"},{"lineNumber":16,"author":{"gitId":"ChubbsBunns"},"content":"                System.out.println(\"______________________________________________\");","lastModifiedDate":"2023-01-16"},{"lineNumber":17,"author":{"gitId":"ChubbsBunns"},"content":"                switch (input) {","lastModifiedDate":"2023-01-19"},{"lineNumber":18,"author":{"gitId":"ChubbsBunns"},"content":"                    case \"list\":","lastModifiedDate":"2023-01-19"},{"lineNumber":19,"author":{"gitId":"ChubbsBunns"},"content":"                        outPutUI.printList(ListOfThings, index);","lastModifiedDate":"2023-02-01"},{"lineNumber":20,"author":{"gitId":"ChubbsBunns"},"content":"                        break;","lastModifiedDate":"2023-01-19"},{"lineNumber":21,"author":{"gitId":"ChubbsBunns"},"content":"                    case \"bye\":","lastModifiedDate":"2023-01-19"},{"lineNumber":22,"author":{"gitId":"ChubbsBunns"},"content":"                        outPutUI.byeByeMessage();","lastModifiedDate":"2023-02-01"},{"lineNumber":23,"author":{"gitId":"ChubbsBunns"},"content":"                        System.exit((0));","lastModifiedDate":"2023-01-16"},{"lineNumber":24,"author":{"gitId":"ChubbsBunns"},"content":"                    case \"todo\":","lastModifiedDate":"2023-01-19"},{"lineNumber":25,"author":{"gitId":"ChubbsBunns"},"content":"                        try {","lastModifiedDate":"2023-01-19"},{"lineNumber":26,"author":{"gitId":"ChubbsBunns"},"content":"                            String restOfString \u003d newScanner.nextLine();","lastModifiedDate":"2023-01-19"},{"lineNumber":27,"author":{"gitId":"ChubbsBunns"},"content":"                            if (restOfString.equals(\"\")) {","lastModifiedDate":"2023-02-01"},{"lineNumber":28,"author":{"gitId":"ChubbsBunns"},"content":"                                throw new DukeException(outPutUI.nullInputErrorMessage(\"Description cannot be Empty\"));","lastModifiedDate":"2023-02-01"},{"lineNumber":29,"author":{"gitId":"ChubbsBunns"},"content":"                            }","lastModifiedDate":"2023-01-19"},{"lineNumber":30,"author":{"gitId":"ChubbsBunns"},"content":"                            else {","lastModifiedDate":"2023-02-01"},{"lineNumber":31,"author":{"gitId":"ChubbsBunns"},"content":"                                Todo newToDo \u003d new Todo(restOfString);","lastModifiedDate":"2023-02-01"},{"lineNumber":32,"author":{"gitId":"ChubbsBunns"},"content":"                                ListOfThings[index] \u003d newToDo;","lastModifiedDate":"2023-02-01"},{"lineNumber":33,"author":{"gitId":"ChubbsBunns"},"content":"                                index +\u003d 1;","lastModifiedDate":"2023-01-19"},{"lineNumber":34,"author":{"gitId":"ChubbsBunns"},"content":"                                outPutUI.addToListTodoMessage(newToDo, index);","lastModifiedDate":"2023-02-01"},{"lineNumber":35,"author":{"gitId":"ChubbsBunns"},"content":"                                break;","lastModifiedDate":"2023-01-19"},{"lineNumber":36,"author":{"gitId":"ChubbsBunns"},"content":"                            }","lastModifiedDate":"2023-01-19"},{"lineNumber":37,"author":{"gitId":"ChubbsBunns"},"content":"                        }","lastModifiedDate":"2023-01-19"},{"lineNumber":38,"author":{"gitId":"ChubbsBunns"},"content":"                        catch (DukeException e) {","lastModifiedDate":"2023-02-01"},{"lineNumber":39,"author":{"gitId":"ChubbsBunns"},"content":"                            System.out.println(e.getMessage());","lastModifiedDate":"2023-01-19"},{"lineNumber":40,"author":{"gitId":"ChubbsBunns"},"content":"                            break;","lastModifiedDate":"2023-01-19"},{"lineNumber":41,"author":{"gitId":"ChubbsBunns"},"content":"                        }","lastModifiedDate":"2023-01-16"},{"lineNumber":42,"author":{"gitId":"ChubbsBunns"},"content":"                    case \"deadline\":","lastModifiedDate":"2023-01-19"},{"lineNumber":43,"author":{"gitId":"ChubbsBunns"},"content":"                        String description \u003d \"\";","lastModifiedDate":"2023-01-19"},{"lineNumber":44,"author":{"gitId":"ChubbsBunns"},"content":"                        while (true) {","lastModifiedDate":"2023-02-01"},{"lineNumber":45,"author":{"gitId":"ChubbsBunns"},"content":"                            String currWord \u003d newScanner.next();","lastModifiedDate":"2023-01-19"},{"lineNumber":46,"author":{"gitId":"ChubbsBunns"},"content":"                            if (currWord.equals(\"/by\")) {","lastModifiedDate":"2023-01-19"},{"lineNumber":47,"author":{"gitId":"ChubbsBunns"},"content":"                                break;","lastModifiedDate":"2023-01-19"},{"lineNumber":48,"author":{"gitId":"ChubbsBunns"},"content":"                            }","lastModifiedDate":"2023-01-16"},{"lineNumber":49,"author":{"gitId":"ChubbsBunns"},"content":"                            else {","lastModifiedDate":"2023-01-19"},{"lineNumber":50,"author":{"gitId":"ChubbsBunns"},"content":"                                description \u003d description.concat(currWord);","lastModifiedDate":"2023-01-19"},{"lineNumber":51,"author":{"gitId":"ChubbsBunns"},"content":"                                description \u003d description.concat(\" \");","lastModifiedDate":"2023-01-19"},{"lineNumber":52,"author":{"gitId":"ChubbsBunns"},"content":"                            }","lastModifiedDate":"2023-01-19"},{"lineNumber":53,"author":{"gitId":"ChubbsBunns"},"content":"                        }","lastModifiedDate":"2023-01-19"},{"lineNumber":54,"author":{"gitId":"ChubbsBunns"},"content":"                        String dueDate \u003d newScanner.nextLine();","lastModifiedDate":"2023-01-19"},{"lineNumber":55,"author":{"gitId":"ChubbsBunns"},"content":"                        if (description.equals(\"\"))","lastModifiedDate":"2023-01-19"},{"lineNumber":56,"author":{"gitId":"ChubbsBunns"},"content":"                        {","lastModifiedDate":"2023-01-16"},{"lineNumber":57,"author":{"gitId":"ChubbsBunns"},"content":"                            System.out.println(outPutUI.nullInputErrorMessage(\"Description cannot be empty :\u003c, please write a description after the word deadline\"));","lastModifiedDate":"2023-02-01"},{"lineNumber":58,"author":{"gitId":"ChubbsBunns"},"content":"                            break;","lastModifiedDate":"2023-01-19"},{"lineNumber":59,"author":{"gitId":"ChubbsBunns"},"content":"                        } else if (dueDate.equals(\"\") ) {","lastModifiedDate":"2023-01-19"},{"lineNumber":60,"author":{"gitId":"ChubbsBunns"},"content":"                            System.out.println(outPutUI.nullInputErrorMessage(\"DueDate cannot be empty :\u003c, please write a the description of a deadline\"));","lastModifiedDate":"2023-02-01"},{"lineNumber":61,"author":{"gitId":"ChubbsBunns"},"content":"                            break;","lastModifiedDate":"2023-01-19"},{"lineNumber":62,"author":{"gitId":"ChubbsBunns"},"content":"                        }","lastModifiedDate":"2023-01-19"},{"lineNumber":63,"author":{"gitId":"ChubbsBunns"},"content":"                        Deadline newDeadline \u003d new Deadline(description, dueDate);","lastModifiedDate":"2023-02-01"},{"lineNumber":64,"author":{"gitId":"ChubbsBunns"},"content":"                        ListOfThings[index] \u003d newDeadline;","lastModifiedDate":"2023-02-01"},{"lineNumber":65,"author":{"gitId":"ChubbsBunns"},"content":"                        index +\u003d 1;","lastModifiedDate":"2023-01-19"},{"lineNumber":66,"author":{"gitId":"ChubbsBunns"},"content":"                        outPutUI.addToListTodoMessage(newDeadline, index);","lastModifiedDate":"2023-02-01"},{"lineNumber":67,"author":{"gitId":"ChubbsBunns"},"content":"                        break;","lastModifiedDate":"2023-01-19"},{"lineNumber":68,"author":{"gitId":"ChubbsBunns"},"content":"                    case \"event\":","lastModifiedDate":"2023-01-19"},{"lineNumber":69,"author":{"gitId":"ChubbsBunns"},"content":"                        String descriptionEvent \u003d \"\";","lastModifiedDate":"2023-01-19"},{"lineNumber":70,"author":{"gitId":"ChubbsBunns"},"content":"                        String startDate \u003d \"\";","lastModifiedDate":"2023-01-19"},{"lineNumber":71,"author":{"gitId":"ChubbsBunns"},"content":"","lastModifiedDate":"2023-01-19"},{"lineNumber":72,"author":{"gitId":"ChubbsBunns"},"content":"                        while (true) {","lastModifiedDate":"2023-01-19"},{"lineNumber":73,"author":{"gitId":"ChubbsBunns"},"content":"                            String currWord \u003d newScanner.next();","lastModifiedDate":"2023-01-19"},{"lineNumber":74,"author":{"gitId":"ChubbsBunns"},"content":"                            if (currWord.equals(\"/from\")) {","lastModifiedDate":"2023-01-19"},{"lineNumber":75,"author":{"gitId":"ChubbsBunns"},"content":"                                break;","lastModifiedDate":"2023-01-19"},{"lineNumber":76,"author":{"gitId":"ChubbsBunns"},"content":"                            } else {","lastModifiedDate":"2023-01-19"},{"lineNumber":77,"author":{"gitId":"ChubbsBunns"},"content":"                                descriptionEvent \u003d descriptionEvent.concat(currWord);","lastModifiedDate":"2023-01-19"},{"lineNumber":78,"author":{"gitId":"ChubbsBunns"},"content":"                                descriptionEvent \u003d descriptionEvent.concat(\" \");","lastModifiedDate":"2023-01-19"},{"lineNumber":79,"author":{"gitId":"ChubbsBunns"},"content":"                            }","lastModifiedDate":"2023-01-19"},{"lineNumber":80,"author":{"gitId":"ChubbsBunns"},"content":"                        }","lastModifiedDate":"2023-01-19"},{"lineNumber":81,"author":{"gitId":"ChubbsBunns"},"content":"                        while (true) {","lastModifiedDate":"2023-01-19"},{"lineNumber":82,"author":{"gitId":"ChubbsBunns"},"content":"                            String currWord \u003d newScanner.next();","lastModifiedDate":"2023-01-19"},{"lineNumber":83,"author":{"gitId":"ChubbsBunns"},"content":"                            if (currWord.equals(\"/to\")) {","lastModifiedDate":"2023-01-19"},{"lineNumber":84,"author":{"gitId":"ChubbsBunns"},"content":"                                break;","lastModifiedDate":"2023-01-16"},{"lineNumber":85,"author":{"gitId":"ChubbsBunns"},"content":"                            } else {","lastModifiedDate":"2023-01-19"},{"lineNumber":86,"author":{"gitId":"ChubbsBunns"},"content":"                                startDate \u003d startDate.concat(currWord);","lastModifiedDate":"2023-01-19"},{"lineNumber":87,"author":{"gitId":"ChubbsBunns"},"content":"                                startDate \u003d startDate.concat(\" \");","lastModifiedDate":"2023-01-19"},{"lineNumber":88,"author":{"gitId":"ChubbsBunns"},"content":"                            }","lastModifiedDate":"2023-01-16"},{"lineNumber":89,"author":{"gitId":"ChubbsBunns"},"content":"                        }","lastModifiedDate":"2023-01-16"},{"lineNumber":90,"author":{"gitId":"ChubbsBunns"},"content":"","lastModifiedDate":"2023-01-19"},{"lineNumber":91,"author":{"gitId":"ChubbsBunns"},"content":"                            String endDate \u003d newScanner.nextLine();","lastModifiedDate":"2023-01-19"},{"lineNumber":92,"author":{"gitId":"ChubbsBunns"},"content":"                            if (endDate.equals(\"\")) {","lastModifiedDate":"2023-01-19"},{"lineNumber":93,"author":{"gitId":"ChubbsBunns"},"content":"                                throw new DukeException(outPutUI.nullInputErrorMessage(\"End Date cannot be empty :\u003c\"));","lastModifiedDate":"2023-02-01"},{"lineNumber":94,"author":{"gitId":"ChubbsBunns"},"content":"                            } else {","lastModifiedDate":"2023-01-19"},{"lineNumber":95,"author":{"gitId":"ChubbsBunns"},"content":"                                Event newEvent \u003d new Event(descriptionEvent, startDate, endDate);","lastModifiedDate":"2023-02-01"},{"lineNumber":96,"author":{"gitId":"ChubbsBunns"},"content":"                                ListOfThings[index] \u003d newEvent;","lastModifiedDate":"2023-02-01"},{"lineNumber":97,"author":{"gitId":"ChubbsBunns"},"content":"                                index +\u003d 1;","lastModifiedDate":"2023-01-19"},{"lineNumber":98,"author":{"gitId":"ChubbsBunns"},"content":"                                outPutUI.addToListTodoMessage(newEvent, index);","lastModifiedDate":"2023-02-01"},{"lineNumber":99,"author":{"gitId":"ChubbsBunns"},"content":"                            }","lastModifiedDate":"2023-01-16"},{"lineNumber":100,"author":{"gitId":"ChubbsBunns"},"content":"","lastModifiedDate":"2023-01-19"},{"lineNumber":101,"author":{"gitId":"ChubbsBunns"},"content":"                        break;","lastModifiedDate":"2023-01-19"},{"lineNumber":102,"author":{"gitId":"ChubbsBunns"},"content":"                    case \"mark\":","lastModifiedDate":"2023-01-19"},{"lineNumber":103,"author":{"gitId":"ChubbsBunns"},"content":"                            int num;","lastModifiedDate":"2023-01-19"},{"lineNumber":104,"author":{"gitId":"ChubbsBunns"},"content":"                            try {","lastModifiedDate":"2023-01-19"},{"lineNumber":105,"author":{"gitId":"ChubbsBunns"},"content":"                                num \u003d newScanner.nextInt();","lastModifiedDate":"2023-01-19"},{"lineNumber":106,"author":{"gitId":"ChubbsBunns"},"content":"                                if (index \u003d\u003d 0) {","lastModifiedDate":"2023-01-19"},{"lineNumber":107,"author":{"gitId":"ChubbsBunns"},"content":"                                    System.out.println(\"There are no items in the list! Please input an item for Pikapi :3\");","lastModifiedDate":"2023-01-19"},{"lineNumber":108,"author":{"gitId":"ChubbsBunns"},"content":"                                    break;","lastModifiedDate":"2023-01-19"},{"lineNumber":109,"author":{"gitId":"ChubbsBunns"},"content":"                                } else if (num \u003e index) {","lastModifiedDate":"2023-01-19"},{"lineNumber":110,"author":{"gitId":"ChubbsBunns"},"content":"                                    System.out.println(\"You do not have that many items yet, Pikapi requests a number less than or equal to \" + index + \" after the word mark\");","lastModifiedDate":"2023-01-19"},{"lineNumber":111,"author":{"gitId":"ChubbsBunns"},"content":"                                    break;","lastModifiedDate":"2023-01-19"},{"lineNumber":112,"author":{"gitId":"ChubbsBunns"},"content":"                                } else if (num \u003c\u003d 0) {","lastModifiedDate":"2023-01-19"},{"lineNumber":113,"author":{"gitId":"ChubbsBunns"},"content":"                                    System.out.println(\"PIKAPII you dont have negative number of tasks silly, please input a number between 1 and \" + index + \" after the word mark\");","lastModifiedDate":"2023-01-19"},{"lineNumber":114,"author":{"gitId":"ChubbsBunns"},"content":"                                    break;","lastModifiedDate":"2023-01-19"},{"lineNumber":115,"author":{"gitId":"ChubbsBunns"},"content":"                                } else {","lastModifiedDate":"2023-01-19"},{"lineNumber":116,"author":{"gitId":"ChubbsBunns"},"content":"                                    marker.markTask(ListOfThings[num - 1]);","lastModifiedDate":"2023-02-01"},{"lineNumber":117,"author":{"gitId":"ChubbsBunns"},"content":"                                    outPutUI.markTaskMessage(ListOfThings[num - 1]);","lastModifiedDate":"2023-02-01"},{"lineNumber":118,"author":{"gitId":"ChubbsBunns"},"content":"                                    break;","lastModifiedDate":"2023-01-19"},{"lineNumber":119,"author":{"gitId":"ChubbsBunns"},"content":"                                }","lastModifiedDate":"2023-01-19"},{"lineNumber":120,"author":{"gitId":"ChubbsBunns"},"content":"                            } catch(InputMismatchException e) {","lastModifiedDate":"2023-02-01"},{"lineNumber":121,"author":{"gitId":"ChubbsBunns"},"content":"                                System.out.println(\"PIKAPII thats not a number! Please input a number after you type mark!\");","lastModifiedDate":"2023-01-19"},{"lineNumber":122,"author":{"gitId":"ChubbsBunns"},"content":"                                //this skip prevents the final catch error (where the cases fall through until command is unrecognized) from being played if there is an incorrect message","lastModifiedDate":"2023-02-01"},{"lineNumber":123,"author":{"gitId":"ChubbsBunns"},"content":"                                newScanner.skip(\"[a-zA-Z1-9]*\");","lastModifiedDate":"2023-01-19"},{"lineNumber":124,"author":{"gitId":"ChubbsBunns"},"content":"                            }","lastModifiedDate":"2023-01-16"},{"lineNumber":125,"author":{"gitId":"ChubbsBunns"},"content":"                            break;","lastModifiedDate":"2023-01-19"},{"lineNumber":126,"author":{"gitId":"ChubbsBunns"},"content":"                    case \"unmark\":","lastModifiedDate":"2023-01-19"},{"lineNumber":127,"author":{"gitId":"ChubbsBunns"},"content":"                        try {","lastModifiedDate":"2023-01-19"},{"lineNumber":128,"author":{"gitId":"ChubbsBunns"},"content":"                            while (true) {","lastModifiedDate":"2023-01-19"},{"lineNumber":129,"author":{"gitId":"ChubbsBunns"},"content":"                                int numUnmarkIndex \u003d newScanner.nextInt();","lastModifiedDate":"2023-01-19"},{"lineNumber":130,"author":{"gitId":"ChubbsBunns"},"content":"                                if (numUnmarkIndex \u003e index) {","lastModifiedDate":"2023-01-19"},{"lineNumber":131,"author":{"gitId":"ChubbsBunns"},"content":"                                    System.out.println(\"You do not have that many items yet, Pikapi requests a correct number less than or equal to \" + index + \" after the word unmark\");","lastModifiedDate":"2023-01-19"},{"lineNumber":132,"author":{"gitId":"ChubbsBunns"},"content":"                                    break;","lastModifiedDate":"2023-01-19"},{"lineNumber":133,"author":{"gitId":"ChubbsBunns"},"content":"                                } else if (numUnmarkIndex \u003c 0) {","lastModifiedDate":"2023-01-19"},{"lineNumber":134,"author":{"gitId":"ChubbsBunns"},"content":"                                    int lowerBound;","lastModifiedDate":"2023-01-19"},{"lineNumber":135,"author":{"gitId":"ChubbsBunns"},"content":"                                    if (index \u003d\u003d 0) {","lastModifiedDate":"2023-02-01"},{"lineNumber":136,"author":{"gitId":"ChubbsBunns"},"content":"                                        lowerBound \u003d 0;","lastModifiedDate":"2023-01-19"},{"lineNumber":137,"author":{"gitId":"ChubbsBunns"},"content":"                                    }","lastModifiedDate":"2023-01-16"},{"lineNumber":138,"author":{"gitId":"ChubbsBunns"},"content":"                                    else {","lastModifiedDate":"2023-02-01"},{"lineNumber":139,"author":{"gitId":"ChubbsBunns"},"content":"                                        lowerBound \u003d 1;","lastModifiedDate":"2023-01-19"},{"lineNumber":140,"author":{"gitId":"ChubbsBunns"},"content":"                                    }","lastModifiedDate":"2023-01-19"},{"lineNumber":141,"author":{"gitId":"ChubbsBunns"},"content":"                                    System.out.println(\"PIKAPII you dont have negative number of tasks silly, please input a number between \" + lowerBound  + \" and \" + index + \" after the word unmark\");","lastModifiedDate":"2023-01-19"},{"lineNumber":142,"author":{"gitId":"ChubbsBunns"},"content":"                                    break;","lastModifiedDate":"2023-01-19"},{"lineNumber":143,"author":{"gitId":"ChubbsBunns"},"content":"                                } else {","lastModifiedDate":"2023-01-19"},{"lineNumber":144,"author":{"gitId":"ChubbsBunns"},"content":"                                    marker.unmarkTask(ListOfThings[numUnmarkIndex - 1]);","lastModifiedDate":"2023-02-01"},{"lineNumber":145,"author":{"gitId":"ChubbsBunns"},"content":"                                    outPutUI.unmarkTaskMessage(ListOfThings[numUnmarkIndex - 1]);","lastModifiedDate":"2023-02-01"},{"lineNumber":146,"author":{"gitId":"ChubbsBunns"},"content":"                                    break;","lastModifiedDate":"2023-01-16"},{"lineNumber":147,"author":{"gitId":"ChubbsBunns"},"content":"                                }","lastModifiedDate":"2023-01-16"},{"lineNumber":148,"author":{"gitId":"ChubbsBunns"},"content":"                            }","lastModifiedDate":"2023-01-16"},{"lineNumber":149,"author":{"gitId":"ChubbsBunns"},"content":"                        } catch (InputMismatchException e) {","lastModifiedDate":"2023-02-01"},{"lineNumber":150,"author":{"gitId":"ChubbsBunns"},"content":"                            System.out.println(\"PIKAPII thats not a number! Please input a number after you type unmark!\");","lastModifiedDate":"2023-01-19"},{"lineNumber":151,"author":{"gitId":"ChubbsBunns"},"content":"                            newScanner.skip(\"[a-zA-Z1-9]*\");","lastModifiedDate":"2023-01-19"},{"lineNumber":152,"author":{"gitId":"ChubbsBunns"},"content":"                        }","lastModifiedDate":"2023-01-16"},{"lineNumber":153,"author":{"gitId":"ChubbsBunns"},"content":"                        break;","lastModifiedDate":"2023-01-19"},{"lineNumber":154,"author":{"gitId":"ChubbsBunns"},"content":"                    default:","lastModifiedDate":"2023-01-19"},{"lineNumber":155,"author":{"gitId":"ChubbsBunns"},"content":"                            System.out.println(input);","lastModifiedDate":"2023-01-19"},{"lineNumber":156,"author":{"gitId":"ChubbsBunns"},"content":"                            throw new DukeException(\"Pikapi is unable to find that command, please type in a correct command\");","lastModifiedDate":"2023-01-19"},{"lineNumber":157,"author":{"gitId":"ChubbsBunns"},"content":"                }","lastModifiedDate":"2023-01-19"},{"lineNumber":158,"author":{"gitId":"ChubbsBunns"},"content":"            }catch(DukeException e) {","lastModifiedDate":"2023-02-01"},{"lineNumber":159,"author":{"gitId":"ChubbsBunns"},"content":"                System.out.println(e.getMessage());","lastModifiedDate":"2023-01-19"},{"lineNumber":160,"author":{"gitId":"ChubbsBunns"},"content":"            }","lastModifiedDate":"2023-01-16"},{"lineNumber":161,"author":{"gitId":"ChubbsBunns"},"content":"        }","lastModifiedDate":"2023-01-16"},{"lineNumber":162,"author":{"gitId":"ChubbsBunns"},"content":"    }","lastModifiedDate":"2023-01-16"},{"lineNumber":163,"author":{"gitId":"ChubbsBunns"},"content":"}","lastModifiedDate":"2023-01-16"}],"authorContributionMap":{"ChubbsBunns":163}},{"path":"src/main/java/Deadline.java","fileType":"java","lines":[{"lineNumber":1,"author":{"gitId":"ChubbsBunns"},"content":"public class Deadline extends Task{","lastModifiedDate":"2023-01-17"},{"lineNumber":2,"author":{"gitId":"ChubbsBunns"},"content":"    protected String by;","lastModifiedDate":"2023-01-17"},{"lineNumber":3,"author":{"gitId":"ChubbsBunns"},"content":"","lastModifiedDate":"2023-01-17"},{"lineNumber":4,"author":{"gitId":"ChubbsBunns"},"content":"    public Deadline(String description, String by) {","lastModifiedDate":"2023-01-17"},{"lineNumber":5,"author":{"gitId":"ChubbsBunns"},"content":"        super(description);","lastModifiedDate":"2023-01-17"},{"lineNumber":6,"author":{"gitId":"ChubbsBunns"},"content":"        this.by \u003d by;","lastModifiedDate":"2023-01-17"},{"lineNumber":7,"author":{"gitId":"ChubbsBunns"},"content":"    }","lastModifiedDate":"2023-01-17"},{"lineNumber":8,"author":{"gitId":"ChubbsBunns"},"content":"","lastModifiedDate":"2023-01-17"},{"lineNumber":9,"author":{"gitId":"ChubbsBunns"},"content":"    @Override","lastModifiedDate":"2023-01-17"},{"lineNumber":10,"author":{"gitId":"ChubbsBunns"},"content":"    public String toString() {","lastModifiedDate":"2023-01-17"},{"lineNumber":11,"author":{"gitId":"ChubbsBunns"},"content":"        return \"[D]\" + \"[\" + this.getStatusIcon() + \"] \"+ super.description.toString() + \"(by:\" + by + \")\";","lastModifiedDate":"2023-01-17"},{"lineNumber":12,"author":{"gitId":"ChubbsBunns"},"content":"    }","lastModifiedDate":"2023-01-17"},{"lineNumber":13,"author":{"gitId":"ChubbsBunns"},"content":"}","lastModifiedDate":"2023-01-17"}],"authorContributionMap":{"ChubbsBunns":13}},{"path":"src/main/java/Duke.java","fileType":"java","lines":[{"lineNumber":1,"author":{"gitId":"-"},"content":"public class Duke {","lastModifiedDate":"2019-07-29"},{"lineNumber":2,"author":{"gitId":"-"},"content":"    public static void main(String[] args) {","lastModifiedDate":"2019-07-29"},{"lineNumber":3,"author":{"gitId":"ChubbsBunns"},"content":"        String logo \u003d \"_________¶¶¥¥¥¶¶¶\\n\"","lastModifiedDate":"2023-01-16"},{"lineNumber":4,"author":{"gitId":"ChubbsBunns"},"content":"                + \"________¶¶¥¥¥¥¥¶¶¶__________________________________________¶¶¶¶¶¶¶¶\\n\"","lastModifiedDate":"2023-01-16"},{"lineNumber":5,"author":{"gitId":"ChubbsBunns"},"content":"                + \"________¶¶¥¥¥¥¥¥¶¶¶_____________________________________¶¶¶¶¶¥¥¥¥¥¶¶\\n\"","lastModifiedDate":"2023-01-16"},{"lineNumber":6,"author":{"gitId":"ChubbsBunns"},"content":"                + \"________¶¶¥¥¥¥¥¥ƒƒ¶¶________________________________¶¶¶¶¥¥¥¥¥¥¥¥¶¶¶¶\\n\"","lastModifiedDate":"2023-01-16"},{"lineNumber":7,"author":{"gitId":"ChubbsBunns"},"content":"                + \"________¶¶¥¥¥¥ƒƒƒƒƒ¶¶___________________________¶¶¶¶ƒƒ¥¥¥¥¥¥¥¥¶¶¶¶\\n\"","lastModifiedDate":"2023-01-16"},{"lineNumber":8,"author":{"gitId":"ChubbsBunns"},"content":"                + \"________¶¶¶ƒƒƒƒƒƒƒƒ§¶¶________________________¶¶ƒƒƒƒƒƒƒ¥¥¥¥¥¶¶¶¶\\n\"","lastModifiedDate":"2023-01-16"},{"lineNumber":9,"author":{"gitId":"ChubbsBunns"},"content":"                + \"_________¶¶¶ƒƒƒƒƒƒ§§¶¶____________________¶¶¶¶ƒƒƒƒƒƒƒƒƒƒ¥¥¶¶¶¶\\n\"","lastModifiedDate":"2023-01-16"},{"lineNumber":10,"author":{"gitId":"ChubbsBunns"},"content":"                + \"___________¶¶ƒƒƒƒƒ§§¶¶__________________¶¶ƒƒƒƒƒƒƒƒƒƒƒƒƒƒ¶¶¶¶\\n\"","lastModifiedDate":"2023-01-16"},{"lineNumber":11,"author":{"gitId":"ChubbsBunns"},"content":"                + \"____________¶¶ƒƒ§§§§¶¶¶¶¶¶¶¶¶¶¶¶¶¶¶¶¶¶¶¶ƒƒƒƒƒƒƒƒƒƒƒƒƒƒ§§¶¶\\n\"","lastModifiedDate":"2023-01-16"},{"lineNumber":12,"author":{"gitId":"ChubbsBunns"},"content":"                + \"_____________¶¶§§§§§§§ƒƒƒƒƒƒƒƒƒƒƒƒƒƒƒƒƒƒƒƒƒƒƒƒƒƒƒƒ§§§§¶¶\\n\"","lastModifiedDate":"2023-01-16"},{"lineNumber":13,"author":{"gitId":"ChubbsBunns"},"content":"                + \"______________¶¶§§§ƒƒƒƒƒƒƒƒƒƒƒƒƒƒƒƒƒƒƒƒƒƒƒƒƒƒ§§§§§¶¶¶¶___________________¶¶¶¶¶¶\\n\"","lastModifiedDate":"2023-01-16"},{"lineNumber":14,"author":{"gitId":"ChubbsBunns"},"content":"                + \"____________¶¶ƒƒƒƒƒƒƒƒƒƒƒƒƒƒƒƒƒƒƒƒƒƒƒƒƒƒƒƒƒƒ§§§¶¶¶____________________¶¶¶ƒƒƒƒƒ¶¶\\n\"","lastModifiedDate":"2023-01-16"},{"lineNumber":15,"author":{"gitId":"ChubbsBunns"},"content":"                + \"__________¶¶ƒƒƒƒƒƒƒƒƒƒƒƒƒƒƒƒƒƒƒƒƒ¶¶¶¶¶¶ƒƒƒƒ§§§¶¶¶___________________¶¶ƒƒƒƒƒƒƒƒ¶¶\\n\"","lastModifiedDate":"2023-01-16"},{"lineNumber":16,"author":{"gitId":"ChubbsBunns"},"content":"                + \"_________¶¶ƒƒ¶¶¶¶¶ƒƒƒƒƒƒƒƒƒƒƒƒƒƒ¶¶__¶¶¶¶ƒƒƒ§§§§§¶¶________________¶¶ƒƒƒƒƒƒƒƒƒƒ¶¶\\n\"","lastModifiedDate":"2023-01-16"},{"lineNumber":17,"author":{"gitId":"ChubbsBunns"},"content":"                + \"________¶¶ƒƒ¶¶__¶¶ƒƒƒƒƒƒƒƒƒƒƒƒƒƒ¶¶¶¶¶¶¶¶ƒƒƒ§§§§§§¶¶___________¶¶¶¶ƒƒƒƒƒƒƒƒ§§§§§§¶¶\\n\"","lastModifiedDate":"2023-01-16"},{"lineNumber":18,"author":{"gitId":"ChubbsBunns"},"content":"                + \"_______¶¶ƒƒƒ¶¶¶¶¶¶ƒƒƒƒƒƒƒƒƒƒƒƒƒƒƒ¶¶¶¶¶¶ƒƒƒƒƒ§§§§§§¶¶________¶¶ƒƒƒƒƒƒƒƒ§§§§§§§§§§¶¶\\n\"","lastModifiedDate":"2023-01-16"},{"lineNumber":19,"author":{"gitId":"ChubbsBunns"},"content":"                + \"_______¶¶ƒƒƒƒ¶¶¶¶ƒƒƒƒƒ¥¥¥ƒƒƒƒƒƒƒƒƒƒƒƒƒƒƒƒ####§§§§§¶¶____¶¶¶¶ƒƒƒƒƒƒƒƒ§§§§§§§§§§§§¶¶\\n\"","lastModifiedDate":"2023-01-16"},{"lineNumber":20,"author":{"gitId":"ChubbsBunns"},"content":"                + \"_______¶¶###ƒƒƒƒƒƒƒƒƒƒƒƒƒƒƒƒƒƒ¥¥ƒƒƒƒƒƒ########§§§§¶¶¶¶¶¶ƒƒƒƒƒƒƒƒ§§§§§§§§§§§§§§§§¶¶\\n\"","lastModifiedDate":"2023-01-16"},{"lineNumber":21,"author":{"gitId":"ChubbsBunns"},"content":"                + \"_______¶¶####ƒƒƒƒƒƒƒƒ¥¥¥¥¥¥¥¥¥¥¥ƒƒƒƒƒƒ########§§¶¶¶¶ƒƒ¶¶¶¶ƒƒƒƒ§§§§§§§§§§§§§§§§§§¶¶\\n\"","lastModifiedDate":"2023-01-16"},{"lineNumber":22,"author":{"gitId":"ChubbsBunns"},"content":"                + \"____¶¶¶¶¶¶###ƒƒƒƒƒƒƒƒƒ¥¥¥#####¥ƒƒƒƒƒƒƒ########¶¶ƒƒ¶¶ƒƒƒƒƒƒ¶¶§§§§§§§§§§§§§§§§§§§§¶¶\\n\"","lastModifiedDate":"2023-01-16"},{"lineNumber":23,"author":{"gitId":"ChubbsBunns"},"content":"                + \"__¶¶¶ƒƒ¶¶¶¶#ƒƒƒƒƒƒƒƒƒƒ¥¥####¥¥ƒƒƒƒƒƒƒƒƒƒ####§§¶¶ƒƒƒƒƒƒƒƒ¶¶¶¶§§§§§§§§§§§§§§§§¶¶¶¶\\n\"","lastModifiedDate":"2023-01-16"},{"lineNumber":24,"author":{"gitId":"ChubbsBunns"},"content":"                + \"_¶¶ƒƒ¶ƒƒƒƒ¶¶ƒƒƒƒƒƒƒƒƒƒƒƒ¥¥¥¥ƒƒƒƒƒƒƒƒƒƒƒƒƒƒ§§¶¶ƒƒƒƒƒƒƒƒƒƒƒƒ¶¶§§§§§§§§§§§§¶¶¶¶\\n\"","lastModifiedDate":"2023-01-16"},{"lineNumber":25,"author":{"gitId":"ChubbsBunns"},"content":"                + \"¶¶ƒƒƒƒƒƒ§§§§¶¶ƒƒƒƒƒƒƒƒƒƒƒƒƒƒƒƒƒƒƒƒƒƒƒƒƒƒƒƒ¶¶ƒƒƒƒƒƒƒƒ§§§§¶¶§§§§§§§§§§¶¶¶¶\\n\";","lastModifiedDate":"2023-01-16"},{"lineNumber":26,"author":{"gitId":"ChubbsBunns"},"content":"","lastModifiedDate":"2023-01-16"},{"lineNumber":27,"author":{"gitId":"ChubbsBunns"},"content":"","lastModifiedDate":"2023-01-16"},{"lineNumber":28,"author":{"gitId":"ChubbsBunns"},"content":"        System.out.println(\"PIKAPIKAPI HELLOO\\n\" + logo);","lastModifiedDate":"2023-01-16"},{"lineNumber":29,"author":{"gitId":"ChubbsBunns"},"content":"        System.out.println(\"Please let Pikapi write you a lists\");","lastModifiedDate":"2023-01-16"},{"lineNumber":30,"author":{"gitId":"ChubbsBunns"},"content":"","lastModifiedDate":"2023-01-16"},{"lineNumber":31,"author":{"gitId":"ChubbsBunns"},"content":"        Addlist addList \u003d new Addlist();","lastModifiedDate":"2023-01-16"},{"lineNumber":32,"author":{"gitId":"ChubbsBunns"},"content":"        addList.AddList();","lastModifiedDate":"2023-01-16"},{"lineNumber":33,"author":{"gitId":"-"},"content":"    }","lastModifiedDate":"2019-07-29"},{"lineNumber":34,"author":{"gitId":"-"},"content":"}","lastModifiedDate":"2019-07-29"}],"authorContributionMap":{"ChubbsBunns":30,"-":4}},{"path":"src/main/java/DukeException.java","fileType":"java","lines":[{"lineNumber":1,"author":{"gitId":"ChubbsBunns"},"content":"public class DukeException extends Exception{","lastModifiedDate":"2023-01-19"},{"lineNumber":2,"author":{"gitId":"ChubbsBunns"},"content":"","lastModifiedDate":"2023-01-19"},{"lineNumber":3,"author":{"gitId":"ChubbsBunns"},"content":"","lastModifiedDate":"2023-01-19"},{"lineNumber":4,"author":{"gitId":"ChubbsBunns"},"content":"","lastModifiedDate":"2023-01-19"},{"lineNumber":5,"author":{"gitId":"ChubbsBunns"},"content":"    public DukeException()","lastModifiedDate":"2023-01-19"},{"lineNumber":6,"author":{"gitId":"ChubbsBunns"},"content":"    {","lastModifiedDate":"2023-01-19"},{"lineNumber":7,"author":{"gitId":"ChubbsBunns"},"content":"        super(\"Pikapi is unable to find this command, please specify either todo, deadline, event, list, mark or unmark\\n\");","lastModifiedDate":"2023-01-19"},{"lineNumber":8,"author":{"gitId":"ChubbsBunns"},"content":"    }","lastModifiedDate":"2023-01-19"},{"lineNumber":9,"author":{"gitId":"ChubbsBunns"},"content":"","lastModifiedDate":"2023-01-19"},{"lineNumber":10,"author":{"gitId":"ChubbsBunns"},"content":"    public DukeException(String message)","lastModifiedDate":"2023-01-19"},{"lineNumber":11,"author":{"gitId":"ChubbsBunns"},"content":"    {","lastModifiedDate":"2023-01-19"},{"lineNumber":12,"author":{"gitId":"ChubbsBunns"},"content":"        super(message);","lastModifiedDate":"2023-01-19"},{"lineNumber":13,"author":{"gitId":"ChubbsBunns"},"content":"    }","lastModifiedDate":"2023-01-19"},{"lineNumber":14,"author":{"gitId":"ChubbsBunns"},"content":"","lastModifiedDate":"2023-01-19"},{"lineNumber":15,"author":{"gitId":"ChubbsBunns"},"content":"}","lastModifiedDate":"2023-01-19"}],"authorContributionMap":{"ChubbsBunns":15}},{"path":"src/main/java/Echo.java","fileType":"java","lines":[{"lineNumber":1,"author":{"gitId":"ChubbsBunns"},"content":"import java.util.Scanner;","lastModifiedDate":"2023-01-16"},{"lineNumber":2,"author":{"gitId":"ChubbsBunns"},"content":"","lastModifiedDate":"2023-01-16"},{"lineNumber":3,"author":{"gitId":"ChubbsBunns"},"content":"public class Echo {","lastModifiedDate":"2023-01-16"},{"lineNumber":4,"author":{"gitId":"ChubbsBunns"},"content":"    public void Echo()","lastModifiedDate":"2023-01-16"},{"lineNumber":5,"author":{"gitId":"ChubbsBunns"},"content":"    {","lastModifiedDate":"2023-01-16"},{"lineNumber":6,"author":{"gitId":"ChubbsBunns"},"content":"        String surprisedPikachuFaceLogo \u003d \"⣿⣿⣿⣿⣿⡏⠉⠛⢿⣿⣿⣿⣿⣿⣿⣿⣿⣿⣿⣿⣿⣿⣿⣿⣿⣿⣿⣿⡿⣿\\n\"","lastModifiedDate":"2023-01-16"},{"lineNumber":7,"author":{"gitId":"ChubbsBunns"},"content":"                + \"⣿⣿⣿⣿⣿⣿⠀⠀⠀⠈⠛⢿⣿⣿⣿⣿⣿⣿⣿⣿⣿⣿⣿⣿⠿⠛⠉⠁⠀⣿\\n\"","lastModifiedDate":"2023-01-16"},{"lineNumber":8,"author":{"gitId":"ChubbsBunns"},"content":"                + \"⣿⣿⣿⣿⣿⣿⣧⡀⠀⠀⠀⠀⠙⠿⠿⠿⠻⠿⠿⠟⠿⠛⠉⠀⠀⠀⠀⠀⣸⣿\\n\"","lastModifiedDate":"2023-01-16"},{"lineNumber":9,"author":{"gitId":"ChubbsBunns"},"content":"                + \"⣿⣿⣿⣿⣿⣿⣿⣷⣄⠀⡀⠀⠀⠀⠀⠀⠀⠀⠀⠀⠀⠀⠀⠀⠀⠀⢀⣴⣿⣿\\n\"","lastModifiedDate":"2023-01-16"},{"lineNumber":10,"author":{"gitId":"ChubbsBunns"},"content":"                + \"⣿⣿⣿⣿⣿⣿⣿⣿⣿⠏⠀⠀⠀⠀⠀⠀⠀⠀⠀⠀⠀⠀⠀⠀⠠⣴⣿⣿⣿⣿\\n\"","lastModifiedDate":"2023-01-16"},{"lineNumber":11,"author":{"gitId":"ChubbsBunns"},"content":"                + \"⣿⣿⣿⣿⣿⣿⣿⣿⡟⠀⠀⢰⣹⡆⠀⠀⠀⠀⠀⠀⣭⣷⠀⠀⠀⠸⣿⣿⣿⣿ \\n\"","lastModifiedDate":"2023-01-16"},{"lineNumber":12,"author":{"gitId":"ChubbsBunns"},"content":"                + \"⣿⣿⣿⣿⣿⣿⣿⣿⠃⠀⠀⠈⠉⠀⠀⠤⠄⠀⠀⠀⠉⠁⠀⠀⠀⠀⢿⣿⣿⣿ \\n\"","lastModifiedDate":"2023-01-16"},{"lineNumber":13,"author":{"gitId":"ChubbsBunns"},"content":"                + \"⣿⣿⣿⣿⣿⣿⣿⣿⢾⣿⣷⠀⠀⠀⠀⡠⠤⢄⠀⠀⠀⠠⣿⣿⣷⠀⢸⣿⣿⣿ \\n\"","lastModifiedDate":"2023-01-16"},{"lineNumber":14,"author":{"gitId":"ChubbsBunns"},"content":"                + \"⣿⣿⣿⣿⣿⣿⣿⣿⡀⠉⠀⠀⠀⠀⠀⢄⠀⢀⠀⠀⠀⠀⠉⠉⠁⠀⠀⣿⣿⣿ \\n\"","lastModifiedDate":"2023-01-16"},{"lineNumber":15,"author":{"gitId":"ChubbsBunns"},"content":"                + \"⣿⣿⣿⣿⣿⣿⣿⣿⣧⠀⠀⠀⠀⠀⠀⠀⠈⠀⠀⠀⠀⠀⠀⠀⠀⠀⠀⢹⣿⣿ \\n\"","lastModifiedDate":"2023-01-16"},{"lineNumber":16,"author":{"gitId":"ChubbsBunns"},"content":"                + \"⣿⣿⣿⣿⣿⣿⣿⣿⣿⠃⠀⠀⠀⠀⠀⠀⠀⠀⠀⠀⠀⠀⠀⠀⠀⠀⠀⢸⣿⣿\\n\";","lastModifiedDate":"2023-01-16"},{"lineNumber":17,"author":{"gitId":"ChubbsBunns"},"content":"","lastModifiedDate":"2023-01-16"},{"lineNumber":18,"author":{"gitId":"ChubbsBunns"},"content":"        Scanner myObj \u003d new Scanner(System.in);","lastModifiedDate":"2023-01-16"},{"lineNumber":19,"author":{"gitId":"ChubbsBunns"},"content":"        System.out.println(\"PIKA is happy you\u0027re back, let me echo some stuff back at you PIKAPI\");","lastModifiedDate":"2023-01-16"},{"lineNumber":20,"author":{"gitId":"ChubbsBunns"},"content":"        while(true)","lastModifiedDate":"2023-01-16"},{"lineNumber":21,"author":{"gitId":"ChubbsBunns"},"content":"        {","lastModifiedDate":"2023-01-16"},{"lineNumber":22,"author":{"gitId":"ChubbsBunns"},"content":"            System.out.println(\"______________________________________________\");","lastModifiedDate":"2023-01-16"},{"lineNumber":23,"author":{"gitId":"ChubbsBunns"},"content":"","lastModifiedDate":"2023-01-16"},{"lineNumber":24,"author":{"gitId":"ChubbsBunns"},"content":"            String inputString \u003d myObj.nextLine();","lastModifiedDate":"2023-01-16"},{"lineNumber":25,"author":{"gitId":"ChubbsBunns"},"content":"            System.out.println(\"______________________________________________\");","lastModifiedDate":"2023-01-16"},{"lineNumber":26,"author":{"gitId":"ChubbsBunns"},"content":"            if (inputString.equals(\"bye\"))","lastModifiedDate":"2023-01-16"},{"lineNumber":27,"author":{"gitId":"ChubbsBunns"},"content":"            {","lastModifiedDate":"2023-01-16"},{"lineNumber":28,"author":{"gitId":"ChubbsBunns"},"content":"                System.out.println(\"    *surprised Pikachu face* \\n\");","lastModifiedDate":"2023-01-16"},{"lineNumber":29,"author":{"gitId":"ChubbsBunns"},"content":"                System.out.println(surprisedPikachuFaceLogo + \"\\n\");","lastModifiedDate":"2023-01-16"},{"lineNumber":30,"author":{"gitId":"ChubbsBunns"},"content":"                System.out.println(\"Pikapi is surprised to see you go, see you soon fwen\\n\");","lastModifiedDate":"2023-01-16"},{"lineNumber":31,"author":{"gitId":"ChubbsBunns"},"content":"                System.exit((0));","lastModifiedDate":"2023-01-16"},{"lineNumber":32,"author":{"gitId":"ChubbsBunns"},"content":"            }","lastModifiedDate":"2023-01-16"},{"lineNumber":33,"author":{"gitId":"ChubbsBunns"},"content":"            else","lastModifiedDate":"2023-01-16"},{"lineNumber":34,"author":{"gitId":"ChubbsBunns"},"content":"            {","lastModifiedDate":"2023-01-16"},{"lineNumber":35,"author":{"gitId":"ChubbsBunns"},"content":"                System.out.println(inputString);","lastModifiedDate":"2023-01-16"},{"lineNumber":36,"author":{"gitId":"ChubbsBunns"},"content":"            }","lastModifiedDate":"2023-01-16"},{"lineNumber":37,"author":{"gitId":"ChubbsBunns"},"content":"        }","lastModifiedDate":"2023-01-16"},{"lineNumber":38,"author":{"gitId":"ChubbsBunns"},"content":"    }","lastModifiedDate":"2023-01-16"},{"lineNumber":39,"author":{"gitId":"ChubbsBunns"},"content":"}","lastModifiedDate":"2023-01-16"}],"authorContributionMap":{"ChubbsBunns":39}},{"path":"src/main/java/Event.java","fileType":"java","lines":[{"lineNumber":1,"author":{"gitId":"ChubbsBunns"},"content":"public class Event extends Task{","lastModifiedDate":"2023-01-17"},{"lineNumber":2,"author":{"gitId":"ChubbsBunns"},"content":"    protected String startDate;","lastModifiedDate":"2023-01-17"},{"lineNumber":3,"author":{"gitId":"ChubbsBunns"},"content":"    protected String endDate;","lastModifiedDate":"2023-01-17"},{"lineNumber":4,"author":{"gitId":"ChubbsBunns"},"content":"","lastModifiedDate":"2023-01-17"},{"lineNumber":5,"author":{"gitId":"ChubbsBunns"},"content":"    public Event(String description, String startDate, String endDate) {","lastModifiedDate":"2023-01-17"},{"lineNumber":6,"author":{"gitId":"ChubbsBunns"},"content":"        super(description);","lastModifiedDate":"2023-01-17"},{"lineNumber":7,"author":{"gitId":"ChubbsBunns"},"content":"        this.startDate \u003d startDate;","lastModifiedDate":"2023-01-17"},{"lineNumber":8,"author":{"gitId":"ChubbsBunns"},"content":"        this.endDate \u003d endDate;","lastModifiedDate":"2023-01-17"},{"lineNumber":9,"author":{"gitId":"ChubbsBunns"},"content":"    }","lastModifiedDate":"2023-01-17"},{"lineNumber":10,"author":{"gitId":"ChubbsBunns"},"content":"","lastModifiedDate":"2023-01-17"},{"lineNumber":11,"author":{"gitId":"ChubbsBunns"},"content":"    @Override","lastModifiedDate":"2023-01-17"},{"lineNumber":12,"author":{"gitId":"ChubbsBunns"},"content":"    public String toString() {","lastModifiedDate":"2023-01-17"},{"lineNumber":13,"author":{"gitId":"ChubbsBunns"},"content":"        return \"[E]\"+ \"[\" + this.getStatusIcon() + \"] \" + super.description.toString() + \"(from: \" + startDate + \"to:\" + endDate + \")\";","lastModifiedDate":"2023-01-17"},{"lineNumber":14,"author":{"gitId":"ChubbsBunns"},"content":"    }","lastModifiedDate":"2023-01-17"},{"lineNumber":15,"author":{"gitId":"ChubbsBunns"},"content":"}","lastModifiedDate":"2023-01-17"}],"authorContributionMap":{"ChubbsBunns":15}},{"path":"src/main/java/Greet.java","fileType":"java","lines":[{"lineNumber":1,"author":{"gitId":"ChubbsBunns"},"content":"import java.io.*;","lastModifiedDate":"2023-01-16"},{"lineNumber":2,"author":{"gitId":"ChubbsBunns"},"content":"import java.util.Scanner;","lastModifiedDate":"2023-01-16"},{"lineNumber":3,"author":{"gitId":"ChubbsBunns"},"content":"public class Greet {","lastModifiedDate":"2023-01-16"},{"lineNumber":4,"author":{"gitId":"ChubbsBunns"},"content":"    public void GreetUser()","lastModifiedDate":"2023-01-16"},{"lineNumber":5,"author":{"gitId":"ChubbsBunns"},"content":"    {","lastModifiedDate":"2023-01-16"},{"lineNumber":6,"author":{"gitId":"ChubbsBunns"},"content":"        System.out.println(\"__________________________________________\");","lastModifiedDate":"2023-01-16"},{"lineNumber":7,"author":{"gitId":"ChubbsBunns"},"content":"        System.out.println(\"Hey person! My name is Duke, that is D U K E Duke\");","lastModifiedDate":"2023-01-16"},{"lineNumber":8,"author":{"gitId":"ChubbsBunns"},"content":"        System.out.println(\"How may I be of your assistance today my friend?\");","lastModifiedDate":"2023-01-16"},{"lineNumber":9,"author":{"gitId":"ChubbsBunns"},"content":"        System.out.println(\"__________________________________________\");","lastModifiedDate":"2023-01-16"},{"lineNumber":10,"author":{"gitId":"ChubbsBunns"},"content":"","lastModifiedDate":"2023-01-16"},{"lineNumber":11,"author":{"gitId":"ChubbsBunns"},"content":"        System.out.println(\"Hello! Aside from greeting I am not able to do much yet, so please check back soon!\");","lastModifiedDate":"2023-01-16"},{"lineNumber":12,"author":{"gitId":"ChubbsBunns"},"content":"        System.out.println((\"Bye bye!\"));","lastModifiedDate":"2023-01-16"},{"lineNumber":13,"author":{"gitId":"ChubbsBunns"},"content":"    }","lastModifiedDate":"2023-01-16"},{"lineNumber":14,"author":{"gitId":"ChubbsBunns"},"content":"}","lastModifiedDate":"2023-01-16"}],"authorContributionMap":{"ChubbsBunns":14}},{"path":"src/main/java/Marker.java","fileType":"java","lines":[{"lineNumber":1,"author":{"gitId":"ChubbsBunns"},"content":"public class Marker {","lastModifiedDate":"2023-02-01"},{"lineNumber":2,"author":{"gitId":"ChubbsBunns"},"content":"    public void markTask(Task task){","lastModifiedDate":"2023-02-01"},{"lineNumber":3,"author":{"gitId":"ChubbsBunns"},"content":"        task.done \u003d true;","lastModifiedDate":"2023-02-01"},{"lineNumber":4,"author":{"gitId":"ChubbsBunns"},"content":"    }","lastModifiedDate":"2023-02-01"},{"lineNumber":5,"author":{"gitId":"ChubbsBunns"},"content":"    public void unmarkTask(Task task){","lastModifiedDate":"2023-02-01"},{"lineNumber":6,"author":{"gitId":"ChubbsBunns"},"content":"        task.done \u003d false;","lastModifiedDate":"2023-02-01"},{"lineNumber":7,"author":{"gitId":"ChubbsBunns"},"content":"    }","lastModifiedDate":"2023-02-01"},{"lineNumber":8,"author":{"gitId":"ChubbsBunns"},"content":"}","lastModifiedDate":"2023-02-01"}],"authorContributionMap":{"ChubbsBunns":8}},{"path":"src/main/java/OutputUI.java","fileType":"java","lines":[{"lineNumber":1,"author":{"gitId":"ChubbsBunns"},"content":"public class OutputUI {","lastModifiedDate":"2023-02-01"},{"lineNumber":2,"author":{"gitId":"ChubbsBunns"},"content":"    String unableToFindPikachuFaceLogo \u003d","lastModifiedDate":"2023-02-01"},{"lineNumber":3,"author":{"gitId":"ChubbsBunns"},"content":"            \"⣿⣿⡶⢄⡀⠀⠀⠀⠀⠀⠀⠀⠀⠀⠀⠀⠀⠀⠀⠀⠀⠀⠀⠀⠀   ⣀⢴⣾⣿⣿\\n\"","lastModifiedDate":"2023-02-01"},{"lineNumber":4,"author":{"gitId":"ChubbsBunns"},"content":"                    + \"⣿⣿⠀⠀⠈⠓⢤⡀⠀⠀⢀⡤⣶⠞⠟⠲⣲⢤⣀⠀⠀⠀⢀⠴⠊⠀⠀⢹⣿⠟\\n\"","lastModifiedDate":"2023-02-01"},{"lineNumber":5,"author":{"gitId":"ChubbsBunns"},"content":"                    + \"⠈⠻⢄⠀⠀⠀⠀⠙⢤⠖⢁⠞⠁⠀⢸⠀⠈⠑⣮⣑⣄⠔⠁⠀⠀⠀⢀⠜⠁⠀\\n\"","lastModifiedDate":"2023-02-01"},{"lineNumber":6,"author":{"gitId":"ChubbsBunns"},"content":"                    + \"⠀⠀⠀⠑⠠⣀⠀⠀⢸⣿⣾⣶⠶⠶⠾⠶⢶⣾⣿⣿⠻⠀⠀⢀⡠⠒⠁⠀⠀⠀\\n\"","lastModifiedDate":"2023-02-01"},{"lineNumber":7,"author":{"gitId":"ChubbsBunns"},"content":"                    + \"⠀⠀⠀⠀⠀⠀⠉⡳⣲⠯⠭⢤⠖⠒⠛⠒⠲⠯⠭⠭⠶⢗⠂⠁⠀⠀⡠⠔⠂⠀\\n\"","lastModifiedDate":"2023-02-01"},{"lineNumber":8,"author":{"gitId":"ChubbsBunns"},"content":"                    + \"⠀⠀⠀⢀⡀⠀⢰⠋⠀⠀⠀⠀⠈⠁⠒⠠⠤⠀⠤⠒⠀⠉⠆⠀⡴⠊⠀⠀⠀⠀\\n\"","lastModifiedDate":"2023-02-01"},{"lineNumber":9,"author":{"gitId":"ChubbsBunns"},"content":"                    + \"⠀⠂⡇⡼⠟⠀⡄⢠⣴⠶⠦⢖⣄⠀⠀⠀⠀⠀⢀⡀⠀⠀⢸⠊⠀⠀⠀⠀⠀⠀\\n\"","lastModifiedDate":"2023-02-01"},{"lineNumber":10,"author":{"gitId":"ChubbsBunns"},"content":"                    + \"⠀⠀⠹⠤⡄⠀⣧⡟⢡⣾⣈⡆⢱⡆⠀⠀⠀⢠⣇⣹⣦⠀⠈⠀⠀⠀⠀⠀⠀⠀\\n\"","lastModifiedDate":"2023-02-01"},{"lineNumber":11,"author":{"gitId":"ChubbsBunns"},"content":"                    + \"⠀⠀⠀⠸⠇⠸⠺⡱⡘⠠⠗⠁⣸⡇⡀⠀⠀⠀⠻⠿⠋⢠⠒⡆⠀⠀⠀⠀⠀⠀\\n\"","lastModifiedDate":"2023-02-01"},{"lineNumber":12,"author":{"gitId":"ChubbsBunns"},"content":"                    + \"⠀⠀⠀⠀⠀⢠⡀⢱⠹⣶⣶⠾⠋⠀⠀⠀⠀⠀⠀⠀⠀⠃⢀⠇⡀⢀⠤⠂⠀⠀\\n\"","lastModifiedDate":"2023-02-01"},{"lineNumber":13,"author":{"gitId":"ChubbsBunns"},"content":"                    + \"⠀⠀⠀⠀⠀⢀⠕⠊⠁⠈⠱⠀⠀⠀⠿⠀⠀⠀⠀⠀⠀⡣⠊⠠⢞⣁⡀⠀⠀⠀\\n\"","lastModifiedDate":"2023-02-01"},{"lineNumber":14,"author":{"gitId":"ChubbsBunns"},"content":"                    + \"⠀⠀⠀⠀⢠⡇⠀⠀⠀⣰⡃⠲⣀⠀⠀⠀⢀⠔⠀⠀⠈⠘⡤⡀⠀⡴⠁⠀⠀\\n\";","lastModifiedDate":"2023-02-01"},{"lineNumber":15,"author":{"gitId":"ChubbsBunns"},"content":"    String surprisedPikachuFaceLogo \u003d","lastModifiedDate":"2023-02-01"},{"lineNumber":16,"author":{"gitId":"ChubbsBunns"},"content":"            \"⣿⣿⣿⣿⣿⡏⠉⠛⢿⣿⣿⣿⣿⣿⣿⣿⣿⣿⣿⣿⣿⣿⣿⣿⣿⣿⣿⣿⡿⣿\\n\"","lastModifiedDate":"2023-02-01"},{"lineNumber":17,"author":{"gitId":"ChubbsBunns"},"content":"                    + \"⣿⣿⣿⣿⣿⣿⠀⠀⠀⠈⠛⢿⣿⣿⣿⣿⣿⣿⣿⣿⣿⣿⣿⣿⠿⠛⠉⠁⠀⣿\\n\"","lastModifiedDate":"2023-02-01"},{"lineNumber":18,"author":{"gitId":"ChubbsBunns"},"content":"                    + \"⣿⣿⣿⣿⣿⣿⣧⡀⠀⠀⠀⠀⠙⠿⠿⠿⠻⠿⠿⠟⠿⠛⠉⠀⠀⠀⠀⠀⣸⣿\\n\"","lastModifiedDate":"2023-02-01"},{"lineNumber":19,"author":{"gitId":"ChubbsBunns"},"content":"                    + \"⣿⣿⣿⣿⣿⣿⣿⣷⣄⠀⡀⠀⠀⠀⠀⠀⠀⠀⠀⠀⠀⠀⠀⠀⠀⠀⢀⣴⣿⣿\\n\"","lastModifiedDate":"2023-02-01"},{"lineNumber":20,"author":{"gitId":"ChubbsBunns"},"content":"                    + \"⣿⣿⣿⣿⣿⣿⣿⣿⣿⠏⠀⠀⠀⠀⠀⠀⠀⠀⠀⠀⠀⠀⠀⠀⠠⣴⣿⣿⣿⣿\\n\"","lastModifiedDate":"2023-02-01"},{"lineNumber":21,"author":{"gitId":"ChubbsBunns"},"content":"                    + \"⣿⣿⣿⣿⣿⣿⣿⣿⡟⠀⠀⢰⣹⡆⠀⠀⠀⠀⠀⠀⣭⣷⠀⠀⠀⠸⣿⣿⣿⣿ \\n\"","lastModifiedDate":"2023-02-01"},{"lineNumber":22,"author":{"gitId":"ChubbsBunns"},"content":"                    + \"⣿⣿⣿⣿⣿⣿⣿⣿⠃⠀⠀⠈⠉⠀⠀⠤⠄⠀⠀⠀⠉⠁⠀⠀⠀⠀⢿⣿⣿⣿ \\n\"","lastModifiedDate":"2023-02-01"},{"lineNumber":23,"author":{"gitId":"ChubbsBunns"},"content":"                    + \"⣿⣿⣿⣿⣿⣿⣿⣿⢾⣿⣷⠀⠀⠀⠀⡠⠤⢄⠀⠀⠀⠠⣿⣿⣷⠀⢸⣿⣿⣿ \\n\"","lastModifiedDate":"2023-02-01"},{"lineNumber":24,"author":{"gitId":"ChubbsBunns"},"content":"                    + \"⣿⣿⣿⣿⣿⣿⣿⣿⡀⠉⠀⠀⠀⠀⠀⢄⠀⢀⠀⠀⠀⠀⠉⠉⠁⠀⠀⣿⣿⣿ \\n\"","lastModifiedDate":"2023-02-01"},{"lineNumber":25,"author":{"gitId":"ChubbsBunns"},"content":"                    + \"⣿⣿⣿⣿⣿⣿⣿⣿⣧⠀⠀⠀⠀⠀⠀⠀⠈⠀⠀⠀⠀⠀⠀⠀⠀⠀⠀⢹⣿⣿ \\n\"","lastModifiedDate":"2023-02-01"},{"lineNumber":26,"author":{"gitId":"ChubbsBunns"},"content":"                    + \"⣿⣿⣿⣿⣿⣿⣿⣿⣿⠃⠀⠀⠀⠀⠀⠀⠀⠀⠀⠀⠀⠀⠀⠀⠀⠀⠀⢸⣿⣿\\n\";","lastModifiedDate":"2023-02-01"},{"lineNumber":27,"author":{"gitId":"ChubbsBunns"},"content":"    String addingToListPikachuLogo \u003d","lastModifiedDate":"2023-02-01"},{"lineNumber":28,"author":{"gitId":"ChubbsBunns"},"content":"            \"░░░░░░░░▀████▀▄▄░░░░░░░░░░░░░░▄█\\n\"","lastModifiedDate":"2023-02-01"},{"lineNumber":29,"author":{"gitId":"ChubbsBunns"},"content":"                    + \"░░░░░░░░░░█▀░░░░▀▀▄▄▄▄▄░░░░▄▄▀▀█  (\\\\ \\n\"","lastModifiedDate":"2023-02-01"},{"lineNumber":30,"author":{"gitId":"ChubbsBunns"},"content":"                    + \"░░▄░░░░░░░░█░░░░░░░░░░▀▀▀▀▄░░▄▀   \\\\\u0027\\\\ \\n\"","lastModifiedDate":"2023-02-01"},{"lineNumber":31,"author":{"gitId":"ChubbsBunns"},"content":"                    + \"░▄▀░▀▄░░░░░░▀▄░░░░░░░░░░░░░░▀▄▀    \\\\\u0027\\\\     __________\\n\"","lastModifiedDate":"2023-02-01"},{"lineNumber":32,"author":{"gitId":"ChubbsBunns"},"content":"                    + \"▄▀░░░░█░░░░░█▀░░░▄█▀▄░░░░░░▄█      / \u0027|   ()_________) \\n\"","lastModifiedDate":"2023-02-01"},{"lineNumber":33,"author":{"gitId":"ChubbsBunns"},"content":"                    + \"▀▄░░░░░▀▄░░█░░░░░▀██▀░░░░░██▄█     \\\\ \u0027/    \\\\ ~~~~~~~~ \\\\ \\n\"","lastModifiedDate":"2023-02-01"},{"lineNumber":34,"author":{"gitId":"ChubbsBunns"},"content":"                    + \"░▀▄░░░░▄▀░█░░░▄██▄░░░▄░░▄░░▀▀░█      \\\\       \\\\ ~~~~~~   \\\\ \\n\"","lastModifiedDate":"2023-02-01"},{"lineNumber":35,"author":{"gitId":"ChubbsBunns"},"content":"                    + \"░░█░░▄▀░░█░░░░▀██▀░░░░▀▀░▀▀░░▄▀      \u003d\u003d).      \\\\__________\\\\ \\n\"","lastModifiedDate":"2023-02-01"},{"lineNumber":36,"author":{"gitId":"ChubbsBunns"},"content":"                    + \"░█░░░█░░█░░░░░░▄▄░░░░░░░░░░░▄▀      (__)       ()__________) \\n\";","lastModifiedDate":"2023-02-01"},{"lineNumber":37,"author":{"gitId":"ChubbsBunns"},"content":"","lastModifiedDate":"2023-02-01"},{"lineNumber":38,"author":{"gitId":"ChubbsBunns"},"content":"    String showingListPikachuLogo \u003d","lastModifiedDate":"2023-02-01"},{"lineNumber":39,"author":{"gitId":"ChubbsBunns"},"content":"            \"░░░░█░▀▄░░░░░░░░░░▄▄███▀░░\\n\"","lastModifiedDate":"2023-02-01"},{"lineNumber":40,"author":{"gitId":"ChubbsBunns"},"content":"                    + \"░░░░█░░░▀▄░▄▄▄▄▄░▄▀░░░█▀░░\\n\"","lastModifiedDate":"2023-02-01"},{"lineNumber":41,"author":{"gitId":"ChubbsBunns"},"content":"                    + \"░░░░░▀▄░░░▀░░░░░▀░░░▄▀░░░░\\n\"","lastModifiedDate":"2023-02-01"},{"lineNumber":42,"author":{"gitId":"ChubbsBunns"},"content":"                    + \"░░░░░░░▌░▄▄░░░▄▄░▐▀▀░░░░░░\\n\"","lastModifiedDate":"2023-02-01"},{"lineNumber":43,"author":{"gitId":"ChubbsBunns"},"content":"                    + \"░░░░░░▐░░█▄░░░▄█░░▌▄▄▀▀▀▀█\\n\"","lastModifiedDate":"2023-02-01"},{"lineNumber":44,"author":{"gitId":"ChubbsBunns"},"content":"                    + \"░░░░░░▌▄▄▀▀░▄░▀▀▄▄▐░░░░░░█\\n\"","lastModifiedDate":"2023-02-01"},{"lineNumber":45,"author":{"gitId":"ChubbsBunns"},"content":"                    + \"░░░▄▀▀▐▀▀░░░░░░░▀▀▌▄▄▄░░░█\\n\"","lastModifiedDate":"2023-02-01"},{"lineNumber":46,"author":{"gitId":"ChubbsBunns"},"content":"                    + \"░░░█░░░▀▄░░░░░░░▄▀░░░░█▀▀▀\\n\"","lastModifiedDate":"2023-02-01"},{"lineNumber":47,"author":{"gitId":"ChubbsBunns"},"content":"                    + \"Pikapi give you your list \\n\";","lastModifiedDate":"2023-02-01"},{"lineNumber":48,"author":{"gitId":"ChubbsBunns"},"content":"","lastModifiedDate":"2023-02-01"},{"lineNumber":49,"author":{"gitId":"ChubbsBunns"},"content":"    public void UnableToFindErrorMessage(String error){","lastModifiedDate":"2023-02-01"},{"lineNumber":50,"author":{"gitId":"ChubbsBunns"},"content":"        System.out.println(unableToFindPikachuFaceLogo + error);","lastModifiedDate":"2023-02-01"},{"lineNumber":51,"author":{"gitId":"ChubbsBunns"},"content":"    }","lastModifiedDate":"2023-02-01"},{"lineNumber":52,"author":{"gitId":"ChubbsBunns"},"content":"","lastModifiedDate":"2023-02-01"},{"lineNumber":53,"author":{"gitId":"ChubbsBunns"},"content":"    private static void printLine(){","lastModifiedDate":"2023-02-01"},{"lineNumber":54,"author":{"gitId":"ChubbsBunns"},"content":"        System.out.println(\"  ____________________________________________________________\");","lastModifiedDate":"2023-02-01"},{"lineNumber":55,"author":{"gitId":"ChubbsBunns"},"content":"    }","lastModifiedDate":"2023-02-01"},{"lineNumber":56,"author":{"gitId":"ChubbsBunns"},"content":"","lastModifiedDate":"2023-02-01"},{"lineNumber":57,"author":{"gitId":"ChubbsBunns"},"content":"    public void markTaskMessage(Task task){","lastModifiedDate":"2023-02-01"},{"lineNumber":58,"author":{"gitId":"ChubbsBunns"},"content":"        System.out.println(addingToListPikachuLogo);","lastModifiedDate":"2023-02-01"},{"lineNumber":59,"author":{"gitId":"ChubbsBunns"},"content":"        System.out.println(\"Pikapi has marked the task as done\\n\");","lastModifiedDate":"2023-02-01"},{"lineNumber":60,"author":{"gitId":"ChubbsBunns"},"content":"        System.out.println(\"[\" + task.getStatusIcon() + \"] \" + task.description);","lastModifiedDate":"2023-02-01"},{"lineNumber":61,"author":{"gitId":"ChubbsBunns"},"content":"    }","lastModifiedDate":"2023-02-01"},{"lineNumber":62,"author":{"gitId":"ChubbsBunns"},"content":"    public void unmarkTaskMessage(Task task){","lastModifiedDate":"2023-02-01"},{"lineNumber":63,"author":{"gitId":"ChubbsBunns"},"content":"        System.out.println(addingToListPikachuLogo);","lastModifiedDate":"2023-02-01"},{"lineNumber":64,"author":{"gitId":"ChubbsBunns"},"content":"        System.out.println(\"Pikapi has unmarked the task\\n\");","lastModifiedDate":"2023-02-01"},{"lineNumber":65,"author":{"gitId":"ChubbsBunns"},"content":"        System.out.println(\"[\" + task.getStatusIcon() + \"] \" + task.description);","lastModifiedDate":"2023-02-01"},{"lineNumber":66,"author":{"gitId":"ChubbsBunns"},"content":"    }","lastModifiedDate":"2023-02-01"},{"lineNumber":67,"author":{"gitId":"ChubbsBunns"},"content":"","lastModifiedDate":"2023-02-01"},{"lineNumber":68,"author":{"gitId":"ChubbsBunns"},"content":"    public void addToListTodoMessage(Todo todo, int index){","lastModifiedDate":"2023-02-01"},{"lineNumber":69,"author":{"gitId":"ChubbsBunns"},"content":"        printLine();","lastModifiedDate":"2023-02-01"},{"lineNumber":70,"author":{"gitId":"ChubbsBunns"},"content":"        System.out.println(addingToListPikachuLogo + \"\\n\" + \"Pikapi add this task:\" + \"\\n\" + \"  [T][ ]\" + todo.description);","lastModifiedDate":"2023-02-01"},{"lineNumber":71,"author":{"gitId":"ChubbsBunns"},"content":"        System.out.println(\"Pikapi sees that now you have \" + index + \" tasks in the list\");","lastModifiedDate":"2023-02-01"},{"lineNumber":72,"author":{"gitId":"ChubbsBunns"},"content":"    }","lastModifiedDate":"2023-02-01"},{"lineNumber":73,"author":{"gitId":"ChubbsBunns"},"content":"","lastModifiedDate":"2023-02-01"},{"lineNumber":74,"author":{"gitId":"ChubbsBunns"},"content":"    public void addToListTodoMessage(Deadline deadline, int index){","lastModifiedDate":"2023-02-01"},{"lineNumber":75,"author":{"gitId":"ChubbsBunns"},"content":"        printLine();","lastModifiedDate":"2023-02-01"},{"lineNumber":76,"author":{"gitId":"ChubbsBunns"},"content":"        System.out.println(addingToListPikachuLogo + \"\\n\" + \"Pikapi add this task: \" + \"\\n\" + \"  [D][ ]\" + deadline.description + \"(by:\" + deadline.by + \")\");","lastModifiedDate":"2023-02-01"},{"lineNumber":77,"author":{"gitId":"ChubbsBunns"},"content":"        System.out.println(\"Pikapi sees that now you have \" + index + \" tasks in the list\");","lastModifiedDate":"2023-02-01"},{"lineNumber":78,"author":{"gitId":"ChubbsBunns"},"content":"    }","lastModifiedDate":"2023-02-01"},{"lineNumber":79,"author":{"gitId":"ChubbsBunns"},"content":"","lastModifiedDate":"2023-02-01"},{"lineNumber":80,"author":{"gitId":"ChubbsBunns"},"content":"    public void addToListTodoMessage(Event event, int index){","lastModifiedDate":"2023-02-01"},{"lineNumber":81,"author":{"gitId":"ChubbsBunns"},"content":"        printLine();","lastModifiedDate":"2023-02-01"},{"lineNumber":82,"author":{"gitId":"ChubbsBunns"},"content":"        System.out.println(addingToListPikachuLogo + \"\\n\" + \"Pikapi add this task: \" + \"\\n\" + \"  [E][ ] \" + event.description + \"(by:\" + event.startDate + \"to\" + event.endDate + \")\");","lastModifiedDate":"2023-02-01"},{"lineNumber":83,"author":{"gitId":"ChubbsBunns"},"content":"        System.out.println(\"Pikapi sees that now you have \" + index + \" tasks in the list\");","lastModifiedDate":"2023-02-01"},{"lineNumber":84,"author":{"gitId":"ChubbsBunns"},"content":"    }","lastModifiedDate":"2023-02-01"},{"lineNumber":85,"author":{"gitId":"ChubbsBunns"},"content":"","lastModifiedDate":"2023-02-01"},{"lineNumber":86,"author":{"gitId":"ChubbsBunns"},"content":"","lastModifiedDate":"2023-02-01"},{"lineNumber":87,"author":{"gitId":"ChubbsBunns"},"content":"    public void printList(Task[] tasks, int numTasks){","lastModifiedDate":"2023-02-01"},{"lineNumber":88,"author":{"gitId":"ChubbsBunns"},"content":"        System.out.println(showingListPikachuLogo);","lastModifiedDate":"2023-02-01"},{"lineNumber":89,"author":{"gitId":"ChubbsBunns"},"content":"        for (int i \u003d 0; i \u003c numTasks; i++){","lastModifiedDate":"2023-02-01"},{"lineNumber":90,"author":{"gitId":"ChubbsBunns"},"content":"            System.out.println((i + 1) + \". \" + tasks[i].toString());","lastModifiedDate":"2023-02-01"},{"lineNumber":91,"author":{"gitId":"ChubbsBunns"},"content":"        }","lastModifiedDate":"2023-02-01"},{"lineNumber":92,"author":{"gitId":"ChubbsBunns"},"content":"    }","lastModifiedDate":"2023-02-01"},{"lineNumber":93,"author":{"gitId":"ChubbsBunns"},"content":"","lastModifiedDate":"2023-02-01"},{"lineNumber":94,"author":{"gitId":"ChubbsBunns"},"content":"    public void byeByeMessage(){","lastModifiedDate":"2023-02-01"},{"lineNumber":95,"author":{"gitId":"ChubbsBunns"},"content":"        System.out.println(\"    *surprised Pikachu face* \\n\");","lastModifiedDate":"2023-02-01"},{"lineNumber":96,"author":{"gitId":"ChubbsBunns"},"content":"        System.out.println(surprisedPikachuFaceLogo + \"\\n\");","lastModifiedDate":"2023-02-01"},{"lineNumber":97,"author":{"gitId":"ChubbsBunns"},"content":"        System.out.println(\"Pikapi is surprised to see you go, see you soon fwen\\n\");","lastModifiedDate":"2023-02-01"},{"lineNumber":98,"author":{"gitId":"ChubbsBunns"},"content":"    }","lastModifiedDate":"2023-02-01"},{"lineNumber":99,"author":{"gitId":"ChubbsBunns"},"content":"","lastModifiedDate":"2023-02-01"},{"lineNumber":100,"author":{"gitId":"ChubbsBunns"},"content":"    public String nullInputErrorMessage(String errorMessage){","lastModifiedDate":"2023-02-01"},{"lineNumber":101,"author":{"gitId":"ChubbsBunns"},"content":"        String message \u003d unableToFindPikachuFaceLogo + \"\\n\" + errorMessage;","lastModifiedDate":"2023-02-01"},{"lineNumber":102,"author":{"gitId":"ChubbsBunns"},"content":"        return message;","lastModifiedDate":"2023-02-01"},{"lineNumber":103,"author":{"gitId":"ChubbsBunns"},"content":"    }","lastModifiedDate":"2023-02-01"},{"lineNumber":104,"author":{"gitId":"ChubbsBunns"},"content":"}","lastModifiedDate":"2023-02-01"}],"authorContributionMap":{"ChubbsBunns":104}},{"path":"src/main/java/Task.java","fileType":"java","lines":[{"lineNumber":1,"author":{"gitId":"ChubbsBunns"},"content":"public class Task {","lastModifiedDate":"2023-01-16"},{"lineNumber":2,"author":{"gitId":"ChubbsBunns"},"content":"    protected String description;","lastModifiedDate":"2023-01-16"},{"lineNumber":3,"author":{"gitId":"ChubbsBunns"},"content":"    protected boolean done;","lastModifiedDate":"2023-01-16"},{"lineNumber":4,"author":{"gitId":"ChubbsBunns"},"content":"","lastModifiedDate":"2023-01-16"},{"lineNumber":5,"author":{"gitId":"ChubbsBunns"},"content":"    public Task(String descriptionInput)","lastModifiedDate":"2023-01-16"},{"lineNumber":6,"author":{"gitId":"ChubbsBunns"},"content":"    {","lastModifiedDate":"2023-01-16"},{"lineNumber":7,"author":{"gitId":"ChubbsBunns"},"content":"        this.description \u003d descriptionInput;","lastModifiedDate":"2023-01-16"},{"lineNumber":8,"author":{"gitId":"ChubbsBunns"},"content":"        this.done \u003d false;","lastModifiedDate":"2023-01-16"},{"lineNumber":9,"author":{"gitId":"ChubbsBunns"},"content":"    }","lastModifiedDate":"2023-01-16"},{"lineNumber":10,"author":{"gitId":"ChubbsBunns"},"content":"","lastModifiedDate":"2023-01-16"},{"lineNumber":11,"author":{"gitId":"ChubbsBunns"},"content":"    public String getStatusIcon()","lastModifiedDate":"2023-01-16"},{"lineNumber":12,"author":{"gitId":"ChubbsBunns"},"content":"    {","lastModifiedDate":"2023-01-16"},{"lineNumber":13,"author":{"gitId":"ChubbsBunns"},"content":"        return (done ? \"X\":\" \");","lastModifiedDate":"2023-01-16"},{"lineNumber":14,"author":{"gitId":"ChubbsBunns"},"content":"    }","lastModifiedDate":"2023-01-16"},{"lineNumber":15,"author":{"gitId":"ChubbsBunns"},"content":"","lastModifiedDate":"2023-01-16"},{"lineNumber":16,"author":{"gitId":"ChubbsBunns"},"content":"}","lastModifiedDate":"2023-01-16"}],"authorContributionMap":{"ChubbsBunns":16}},{"path":"src/main/java/Todo.java","fileType":"java","lines":[{"lineNumber":1,"author":{"gitId":"ChubbsBunns"},"content":"public class Todo extends Task{","lastModifiedDate":"2023-01-17"},{"lineNumber":2,"author":{"gitId":"ChubbsBunns"},"content":"    protected String by;","lastModifiedDate":"2023-01-17"},{"lineNumber":3,"author":{"gitId":"ChubbsBunns"},"content":"","lastModifiedDate":"2023-01-17"},{"lineNumber":4,"author":{"gitId":"ChubbsBunns"},"content":"    public Todo(String description) {","lastModifiedDate":"2023-01-17"},{"lineNumber":5,"author":{"gitId":"ChubbsBunns"},"content":"        super(description);","lastModifiedDate":"2023-01-17"},{"lineNumber":6,"author":{"gitId":"ChubbsBunns"},"content":"    }","lastModifiedDate":"2023-01-17"},{"lineNumber":7,"author":{"gitId":"ChubbsBunns"},"content":"","lastModifiedDate":"2023-01-17"},{"lineNumber":8,"author":{"gitId":"ChubbsBunns"},"content":"    @Override","lastModifiedDate":"2023-01-17"},{"lineNumber":9,"author":{"gitId":"ChubbsBunns"},"content":"    public String toString() {","lastModifiedDate":"2023-01-17"},{"lineNumber":10,"author":{"gitId":"ChubbsBunns"},"content":"        return \"[T]\" + \"[\" + this.getStatusIcon() + \"]\" + super.description.toString();","lastModifiedDate":"2023-01-17"},{"lineNumber":11,"author":{"gitId":"ChubbsBunns"},"content":"    }","lastModifiedDate":"2023-01-17"},{"lineNumber":12,"author":{"gitId":"ChubbsBunns"},"content":"}","lastModifiedDate":"2023-01-17"}],"authorContributionMap":{"ChubbsBunns":12}}]
