{"authorDailyContributionsMap":{"LimHongYao":[{"date":"2023-01-18","commitResults":[{"hash":"a63c9f71c58715075586b4a90e7350636e0826e0","messageTitle":"Level-0","messageBody":"","tags":["Level-0"],"fileTypesAndContributionMap":{"java":{"insertions":5,"deletions":6}}}]},{"date":"2023-01-27","commitResults":[{"hash":"ef8d231475c0e1288496d48269d5bc485ce35ea6","messageTitle":"Added echo Changed Duke\u0027s Name","messageBody":"","tags":["Level-1"],"fileTypesAndContributionMap":{"java":{"insertions":16,"deletions":3}}},{"hash":"bdd7c9d91f120f423920230abb575461d02ef8a9","messageTitle":"Added list functionality","messageBody":"","tags":["Level-2"],"fileTypesAndContributionMap":{"java":{"insertions":22,"deletions":2}}}]},{"date":"2023-02-01","commitResults":[{"hash":"9d947097ad661781e7ec82c9fe0c657226140e89","messageTitle":"Added ability to mark and unmark as done Improved handling of commands by splitting user input Changed to use Tasks classes","messageBody":"","tags":["Level-3","A-CodingStandard"],"fileTypesAndContributionMap":{"java":{"insertions":126,"deletions":15}}}]},{"date":"2023-02-10","commitResults":[{"hash":"a3a43470403d361b9f286370a4d979ea05dd1301","messageTitle":"Added deadline, event, todo types for list objects","messageBody":"","tags":["Level-4"],"fileTypesAndContributionMap":{"java":{"insertions":164,"deletions":46}}},{"hash":"c711aeb4190636a067efef8b3dff3aafe5e591dc","messageTitle":"fixed coding standard issues","messageBody":"","tags":["A-CodeQuality"],"fileTypesAndContributionMap":{"java":{"insertions":5,"deletions":3}}},{"hash":"28406be17bef1a371a3498e6cb5c176dc466f5e5","messageTitle":"added bad input handling added immediate prompt for missing information reworked the terrible code in getStartEnd","messageBody":"","fileTypesAndContributionMap":{"java":{"insertions":46,"deletions":38}}}]},{"date":"2023-02-24","commitResults":[{"hash":"6cf1e94a580a81fbd246a6adb18c9ef3f910043b","messageTitle":"added delete functionality to list","messageBody":"","fileTypesAndContributionMap":{"java":{"insertions":30,"deletions":3}}}]},{"date":"2023-02-27","commitResults":[{"hash":"e3a2df52830e8a1b2fa6068fc92c351a9d3216f1","messageTitle":"added tasklist export functionality fixed minor presentation error in event","messageBody":"","fileTypesAndContributionMap":{"java":{"insertions":26,"deletions":1}}}]},{"date":"2023-03-01","commitResults":[{"hash":"e0bf091bf007230bf36fba1496df5df51d462a40","messageTitle":"reverted desktop export path to relative /out path introduced some constants introduced file path printout in event of export failure","messageBody":"","fileTypesAndContributionMap":{"java":{"insertions":16,"deletions":10}}},{"hash":"44155f7c6a5a539a414886457957baf61892b80a","messageTitle":"packaged files removed redundanct \"add\" method in Duke.java","messageBody":"","tags":["A-Packages"],"fileTypesAndContributionMap":{"java":{"insertions":16,"deletions":6}}},{"hash":"95409e72cdb03bca7d5d59b80e95026a8288c81b","messageTitle":"moved some methods to Ui class","messageBody":"","fileTypesAndContributionMap":{"java":{"insertions":81,"deletions":68}}},{"hash":"fd05d8e18573b940ff224073e4d11f28ac7f8155","messageTitle":"rewrote and combined mark/unmark methos","messageBody":"","fileTypesAndContributionMap":{"java":{"insertions":15,"deletions":71}}}]},{"date":"2023-03-03","commitResults":[{"hash":"bc51fbb9c7c378771dafaf635942e17a83c6bc06","messageTitle":"Moved switch cases into OOP Reformatted event and deadline displays","messageBody":"","tags":["A-MoreOOP"],"fileTypesAndContributionMap":{"java":{"insertions":91,"deletions":57}}},{"hash":"81192bc195612b5b5fed4d071dcd5cbe63645712","messageTitle":"added search functionality","messageBody":"","fileTypesAndContributionMap":{"java":{"insertions":52,"deletions":10}}}]}]},"authorFileTypeContributionMap":{"LimHongYao":{"java":434,"md":0,"fxml":0,"sh":0,"bat":0,"gradle":0,"txt":0}},"authorContributionVariance":{"LimHongYao":4340.24},"authorDisplayNameMap":{"LimHongYao":"CS2113-F13-1 LIM .. YAO"}}
