{"authorDailyContributionsMap":{"TopGun2001":[{"date":"2023-01-28","commitResults":[{"hash":"c85dc79dd8f201868a263106c791bed6c8b3c26f","messageTitle":"Committing Level 0","messageBody":"","tags":["Level-0"],"fileTypesAndContributionMap":{"java":{"insertions":18,"deletions":0}}},{"hash":"765e4c14dccfaf9773393d6eeb8bbfa7e1680714","messageTitle":"Committing Level-1","messageBody":"","tags":["Level-1"],"fileTypesAndContributionMap":{"java":{"insertions":32,"deletions":4}}},{"hash":"43c3f234c1325dadf90fce3f634d1f71e7d22248","messageTitle":"Committing Level-2","messageBody":"","tags":["Level-2"],"fileTypesAndContributionMap":{"java":{"insertions":24,"deletions":22}}},{"hash":"d05a2687038c103567d9999ced04ac4fbaed5b25","messageTitle":"Committing Level-3","messageBody":"","tags":["Level-3"],"fileTypesAndContributionMap":{"java":{"insertions":56,"deletions":11}}},{"hash":"ab25ca2b72b964631a9acc8610dd36d22b37ccf8","messageTitle":"Committing   A-CodingStandard","messageBody":"","tags":["A-CodingStandard"],"fileTypesAndContributionMap":{"java":{"insertions":21,"deletions":15}}},{"hash":"6c9774a562b3235c6a3f6eb1a70da37c417ffa56","messageTitle":"Just removed the extra lines","messageBody":"","fileTypesAndContributionMap":{"java":{"insertions":1,"deletions":7}}}]},{"date":"2023-01-29","commitResults":[{"hash":"dea65e222303ba86daa379e119f27427e5f35080","messageTitle":"Delete Duke.java","messageBody":"","fileTypesAndContributionMap":{"java":{"insertions":0,"deletions":10}}}]},{"date":"2023-02-01","commitResults":[{"hash":"6a58d509365ce1535b34630acc7270dcd4c7829c","messageTitle":"Added new classes: Todo, Deadline, Event","messageBody":"","fileTypesAndContributionMap":{"java":{"insertions":57,"deletions":4}}},{"hash":"37d26120da5fed4d4e50f222a7dba6ae5b04e134","messageTitle":"Committing Level 4","messageBody":"","tags":["Level-4"],"fileTypesAndContributionMap":{"java":{"insertions":44,"deletions":29}}}]},{"date":"2023-02-02","commitResults":[{"hash":"dee0189decc22ad4bf12a8e250d38c8755c39f24","messageTitle":"Committing A-CodeQuality","messageBody":"","tags":["A-CodeQuality"],"fileTypesAndContributionMap":{"java":{"insertions":100,"deletions":71}}}]},{"date":"2023-02-03","commitResults":[{"hash":"011ee6cb2b9e221273c49cad3d351be89297e9db","messageTitle":"Committing new changes to code after Peer Review","messageBody":"","fileTypesAndContributionMap":{"java":{"insertions":56,"deletions":64}}},{"hash":"49302335bc075a60453fa07791eff43385bbdaf2","messageTitle":"Committing A-TextUiTesting \u0026 few other code quality/style changes","messageBody":"","tags":["A-TextUiTesting"],"fileTypesAndContributionMap":{"txt":{"insertions":4,"deletions":0},"java":{"insertions":3,"deletions":3},"bat":{"insertions":1,"deletions":1},"sh":{"insertions":1,"deletions":1}}}]},{"date":"2023-02-08","commitResults":[{"hash":"2a5fd8f10be40aff1f8e93250c56459da514871c","messageTitle":"Committing Level-5","messageBody":"","fileTypesAndContributionMap":{"java":{"insertions":111,"deletions":31}}}]},{"date":"2023-02-10","commitResults":[{"hash":"73b16bfa52a00ce16b68de77609ec986db22d0da","messageTitle":"Adding A-Packages","messageBody":"","tags":["A-Packages"],"fileTypesAndContributionMap":{"java":{"insertions":41,"deletions":17},"bat":{"insertions":1,"deletions":1}}}]},{"date":"2023-02-16","commitResults":[{"hash":"c317c77e838cfd5b79db8e39b952f37d3e9d46ba","messageTitle":"adding A-Collection","messageBody":"","tags":["A-Collections"],"fileTypesAndContributionMap":{"java":{"insertions":83,"deletions":45}}}]},{"date":"2023-02-17","commitResults":[{"hash":"1baa40577ed0ddb1d7b00f59215cd95a04ce2039","messageTitle":"New Commits","messageBody":"","fileTypesAndContributionMap":{"java":{"insertions":5,"deletions":5}}},{"hash":"18621398c014b9a0434a2299b4d1c7d70551ad57","messageTitle":"Committing Level-6","messageBody":"","tags":["Level-6"],"fileTypesAndContributionMap":{"java":{"insertions":3,"deletions":3}}},{"hash":"a528b3002b3c02f1d1cbb1ce67b7158be06b96a2","messageTitle":"level-7","messageBody":"","fileTypesAndContributionMap":{"java":{"insertions":50,"deletions":10}}},{"hash":"2ada217d104b05809db999558a88f330edc2c2ca","messageTitle":"Latest","messageBody":"","tags":["A-Jar"],"fileTypesAndContributionMap":{"java":{"insertions":14,"deletions":3}}}]},{"date":"2023-02-26","commitResults":[{"hash":"22ccfc0ac98472383ebbc3fec80f2c52768a5b7b","messageTitle":"Finally finished Level-8 after 6 hours. CS2113 is fun anyways.","messageBody":"","fileTypesAndContributionMap":{"java":{"insertions":330,"deletions":260},"bat":{"insertions":1,"deletions":1}}},{"hash":"201d150bacf0b5b85d42ad92059386d693867ff1","messageTitle":"Adding A-MoreOOP","messageBody":"","tags":["A-MoreOOP"],"fileTypesAndContributionMap":{"java":{"insertions":10,"deletions":15}}},{"hash":"de818e4df8e6e55a265c37415d2843175ad350eb","messageTitle":"Adding A-MoreOOP","messageBody":"","fileTypesAndContributionMap":{"java":{"insertions":0,"deletions":1}}},{"hash":"c0edd8083648a6e867e06f59267829dcc8de296b","messageTitle":"Added Level-8","messageBody":"","tags":["Level-8"],"fileTypesAndContributionMap":{"java":{"insertions":45,"deletions":10}}},{"hash":"041af49354633d5863ebd3c377c770ad5a93655f","messageTitle":"Added Level-9","messageBody":"","tags":["Level-9"],"fileTypesAndContributionMap":{"java":{"insertions":38,"deletions":0}}},{"hash":"d3cc7d5e36c808268e97394fd6d13901f35ffcf4","messageTitle":"Added java documentation for all classes","messageBody":"","tags":["A-JavaDoc"],"fileTypesAndContributionMap":{"java":{"insertions":318,"deletions":77}}},{"hash":"9ed4eeba88fd97e5ffb8bd5a061f2dc081438850","messageTitle":"Update README.md","messageBody":"","tags":["A-UserGuide","A-Release"],"fileTypesAndContributionMap":{"md":{"insertions":185,"deletions":14}}}]},{"date":"2023-03-03","commitResults":[{"hash":"c9f4e86d75b7bd6ebfbbab6b4494032725ea27e8","messageTitle":"Added new changes","messageBody":"","fileTypesAndContributionMap":{"java":{"insertions":2,"deletions":1}}}]}]},"authorFileTypeContributionMap":{"TopGun2001":{"java":743,"md":185,"fxml":0,"sh":1,"bat":1,"gradle":0,"txt":4}},"authorContributionVariance":{"TopGun2001":34945.35},"authorDisplayNameMap":{"TopGun2001":"CS2113-F10-3 SURE.. RAM"}}
