{"authorDailyContributionsMap":{"SpawnageLoong":[{"date":"2023-01-18","commitResults":[{"hash":"3c0b22eab99a3b5cba4b2576701bef437e204eb5","messageTitle":"Complete Level-0","messageBody":"","tags":["Level-0"],"fileTypesAndContributionMap":{"java":{"insertions":9,"deletions":6}}}]},{"date":"2023-01-25","commitResults":[{"hash":"f59b6c26168c4394d038539597b8fafdfb0e0b02","messageTitle":"Complete Level-1","messageBody":"","tags":["Level-1"],"fileTypesAndContributionMap":{"java":{"insertions":18,"deletions":1}}}]},{"date":"2023-01-26","commitResults":[{"hash":"a8873fc28709e42f37a127c4c91dc93ec3d2a273","messageTitle":"Complete Level-2","messageBody":"","tags":["Level-2"],"fileTypesAndContributionMap":{"java":{"insertions":25,"deletions":2}}},{"hash":"fefdd737b4c9b62dde7d46342d717efb69a9ced4","messageTitle":"Complete Level-3","messageBody":"","tags":["Level-3","A-CodingStandard"],"fileTypesAndContributionMap":{"java":{"insertions":78,"deletions":31}}},{"hash":"f1b1b80458293f5dbb124e6315486ca62528ecf6","messageTitle":"Follow coding standards","messageBody":"","fileTypesAndContributionMap":{"java":{"insertions":27,"deletions":28}}}]},{"date":"2023-01-27","commitResults":[{"hash":"b11074274c55273ee5fd9759a0af6b3006d3c80d","messageTitle":"Improve Code Quality","messageBody":"","fileTypesAndContributionMap":{"java":{"insertions":5,"deletions":4}}},{"hash":"189898d8bc3e3b4b925bc09dee1bf18622fcfbc2","messageTitle":"Refactor code","messageBody":"","fileTypesAndContributionMap":{"java":{"insertions":23,"deletions":14}}}]},{"date":"2023-01-31","commitResults":[{"hash":"3f341d82f93dca4bb34e4a9c7ac45e7134db8359","messageTitle":"Add placeholder Deadline and Event classes","messageBody":"","fileTypesAndContributionMap":{"java":{"insertions":86,"deletions":34},"bat":{"insertions":1,"deletions":1},"md":{"insertions":2,"deletions":2}}},{"hash":"e9a2fb15ea6e533d25503062465e8de4f76b29aa","messageTitle":"Add ToDo, Deadline and Event","messageBody":"","tags":["Level-4","A-CodeQuality"],"fileTypesAndContributionMap":{"java":{"insertions":73,"deletions":22}}}]},{"date":"2023-02-06","commitResults":[{"hash":"c18202c22149ad1d55c781dd2204e64e4f0480ed","messageTitle":"Extract print methods to Printer","messageBody":"","fileTypesAndContributionMap":{"java":{"insertions":25,"deletions":12}}},{"hash":"672f37238c092ec7c0da0dc80ff7fad50bd4b8be","messageTitle":"Add line wrapping","messageBody":"","fileTypesAndContributionMap":{"java":{"insertions":2,"deletions":1}}},{"hash":"95c41abd2a465c1a5466c15525661fe609737a11","messageTitle":"Add basic exceptions","messageBody":"","fileTypesAndContributionMap":{"java":{"insertions":93,"deletions":66}}},{"hash":"a41806438c1f4f977cb977641fd30ff0e1c9aab6","messageTitle":"Add noArgsError","messageBody":"","fileTypesAndContributionMap":{"java":{"insertions":10,"deletions":5}}},{"hash":"a532a4ed0de919572385ae1498f639fa5689c771","messageTitle":"Extract addToList to Printer","messageBody":"","fileTypesAndContributionMap":{"java":{"insertions":9,"deletions":6}}},{"hash":"45016ef03b4103541c8684ecd7198cd5d3a6942a","messageTitle":"Create package: shizuka","messageBody":"","fileTypesAndContributionMap":{"java":{"insertions":15,"deletions":5}}}]},{"date":"2023-02-13","commitResults":[{"hash":"a7db8fc6b919d2c274d7c89968289d5415ecb1a5","messageTitle":"Change todoList to non-static","messageBody":"","fileTypesAndContributionMap":{"java":{"insertions":29,"deletions":24}}},{"hash":"b18203b65ebf5555a515ef7ba7453b6b959be808","messageTitle":"Change todoList to ArrayList","messageBody":"","fileTypesAndContributionMap":{"java":{"insertions":14,"deletions":13}}},{"hash":"9f6c327db731236e2e9b08b7c9bcf167531c2052","messageTitle":"Add delete function","messageBody":"","fileTypesAndContributionMap":{"java":{"insertions":15,"deletions":0}}},{"hash":"e7880c90b002d49f5f74b798884087d3e80e8b66","messageTitle":"Add non-functional save","messageBody":"","fileTypesAndContributionMap":{"java":{"insertions":42,"deletions":0}}},{"hash":"102bc77656b9303c9c71bdfde9ac819918d48e59","messageTitle":"Save function working","messageBody":"","fileTypesAndContributionMap":{"java":{"insertions":9,"deletions":1}}},{"hash":"b787223b8dacc29172843168180c0930e959c07c","messageTitle":"Fix missing bracket","messageBody":"","tags":["Level-7"],"fileTypesAndContributionMap":{"java":{"insertions":1,"deletions":0}}},{"hash":"95808a213bb2ab227dde3cb45e6abdf28976377c","messageTitle":"Make todos final","messageBody":"","tags":["A-Jar"],"fileTypesAndContributionMap":{"java":{"insertions":1,"deletions":1}}}]},{"date":"2023-02-16","commitResults":[{"hash":"46309ba1da9e63809106011fdc944268db749f47","messageTitle":"Rename WriteToFile to FileManager","messageBody":"","fileTypesAndContributionMap":{"java":{"insertions":2,"deletions":2}}},{"hash":"1c3b7ca8dd3281e0471a3834de9b9b5928b04d07","messageTitle":"Add methods to print file-related Strings","messageBody":"","fileTypesAndContributionMap":{"java":{"insertions":30,"deletions":1}}},{"hash":"1bfea77a7ebbe23c4b58c4655725be40c20028d5","messageTitle":"Change save file formatting","messageBody":"","fileTypesAndContributionMap":{"java":{"insertions":27,"deletions":8}}},{"hash":"2fd529f5321b53f8744415e59998676d373f700e","messageTitle":"Add line separator to tasks","messageBody":"","fileTypesAndContributionMap":{"java":{"insertions":4,"deletions":3}}},{"hash":"8db836c3892f2123fb1b086e6b7f5a0bfc7a64cf","messageTitle":"Add Load methods","messageBody":"","fileTypesAndContributionMap":{"java":{"insertions":85,"deletions":26}}}]},{"date":"2023-02-28","commitResults":[{"hash":"7bd3f0ae371d806829586d5b1f1167a53d6b5fb7","messageTitle":"Add find function","messageBody":"","fileTypesAndContributionMap":{"java":{"insertions":19,"deletions":0}}},{"hash":"28396c07c57ab9c73764efe83b7e325f11ffde99","messageTitle":"Add JavaDocs comments","messageBody":"","fileTypesAndContributionMap":{"java":{"insertions":82,"deletions":0}}},{"hash":"6f31523b189a7307bef71dd07ef7b0caddbffb18","messageTitle":"Add JavaDocs comments","messageBody":"","fileTypesAndContributionMap":{"java":{"insertions":44,"deletions":0}}},{"hash":"f6ed0035634d8b1d8b661561f2678d64e8cc7044","messageTitle":"Update User Guide","messageBody":"","fileTypesAndContributionMap":{"md":{"insertions":66,"deletions":15}}}]},{"date":"2023-03-01","commitResults":[{"hash":"d2e876bbd1e96389e180b92e7bdad847a1852e23","messageTitle":"Refactor Printer to UI","messageBody":"","fileTypesAndContributionMap":{"java":{"insertions":21,"deletions":21}}},{"hash":"57e50a094316a8cfe9bd48196d7833b13e4a6f81","messageTitle":"Refactor FileManager to Storage","messageBody":"","fileTypesAndContributionMap":{"java":{"insertions":3,"deletions":3}}},{"hash":"b3e2566c94f288ba9a1c7881f277029b00d84ad7","messageTitle":"Improve coding standards","messageBody":"","fileTypesAndContributionMap":{"java":{"insertions":4,"deletions":2}}},{"hash":"7efaa07cd6ae1fc0e13a4166c08e159283d0ec3c","messageTitle":"Extract FILE_PATH to Storage","messageBody":"","fileTypesAndContributionMap":{"java":{"insertions":24,"deletions":4}}},{"hash":"f83c0a716fbbb9d30c71ec44c84450d6223911ca","messageTitle":"Extract basic command and parser methods","messageBody":"","fileTypesAndContributionMap":{"java":{"insertions":39,"deletions":25}}},{"hash":"9855c3b9c2b53568ab1097b4381d8d659e9e698c","messageTitle":"Extract command and parsing methods","messageBody":"","fileTypesAndContributionMap":{"java":{"insertions":131,"deletions":82}}}]}]},"authorFileTypeContributionMap":{"SpawnageLoong":{"java":677,"md":57,"fxml":0,"sh":0,"bat":1,"gradle":0,"txt":0}},"authorContributionVariance":{"SpawnageLoong":6877.932},"authorDisplayNameMap":{"SpawnageLoong":"CS2113-T11-3 RICH.. JUN"}}
