{"authorDailyContributionsMap":{"Rayleigh47":[{"date":"2023-01-17","commitResults":[{"hash":"3e3587c9f1704021a69fc7c4c27b8020034e0213","messageTitle":"Added Conversation.java Updated Duke.java","messageBody":"","fileTypesAndContributionMap":{"java":{"insertions":26,"deletions":0}}}]},{"date":"2023-01-24","commitResults":[{"hash":"3a54d084a7cb98587d2d388cbafe3afce1c3ae4a","messageTitle":"Implement Level-1","messageBody":"","tags":["Level-1"],"fileTypesAndContributionMap":{"java":{"insertions":24,"deletions":8}}},{"hash":"02b291517d82f4ec4925915b5fe2e3fb61251de4","messageTitle":"Implement Level-2","messageBody":"","tags":["Level-2"],"fileTypesAndContributionMap":{"java":{"insertions":14,"deletions":5}}},{"hash":"e930c866744e37bb86e8fb7a0f1ec040166a0612","messageTitle":"Implement Level-3","messageBody":"","tags":["Level-3"],"fileTypesAndContributionMap":{"java":{"insertions":36,"deletions":3}}}]},{"date":"2023-01-29","commitResults":[{"hash":"bf079faf78c510d368d32946abb6a1c707b39220","messageTitle":"Cleaned up code according to coding standard","messageBody":"","tags":["A-CodingStandard"],"fileTypesAndContributionMap":{"java":{"insertions":71,"deletions":36}}}]},{"date":"2023-02-01","commitResults":[{"hash":"fc0e07f3ec151708c69a711a6b1529efae303522","messageTitle":"Implement Level-4 and some SLAP","messageBody":"","tags":["Level-4"],"fileTypesAndContributionMap":{"java":{"insertions":97,"deletions":34}}}]},{"date":"2023-02-02","commitResults":[{"hash":"a152f14ed8f2bf54378929d890b933d68b3e4234","messageTitle":"Implemented text UI testing and improved code quality","messageBody":"","tags":["A-TextUiTesting","A-CodeQuality"],"fileTypesAndContributionMap":{"txt":{"insertions":6,"deletions":0},"java":{"insertions":28,"deletions":27}}}]},{"date":"2023-02-07","commitResults":[{"hash":"6d31a1c86efa54a6e6d11799744720eb1c1fc4df","messageTitle":"updated exception handling","messageBody":"","fileTypesAndContributionMap":{"java":{"insertions":19,"deletions":5}}},{"hash":"52c868dc2688dc739ee3489b936d62a0634aaf8c","messageTitle":"implemented packages","messageBody":"","fileTypesAndContributionMap":{"java":{"insertions":21,"deletions":2}}},{"hash":"59386eab80eab0e06a67dd7bfe472023a743d810","messageTitle":"implemented packages","messageBody":"","fileTypesAndContributionMap":{"java":{"insertions":6,"deletions":6}}}]},{"date":"2023-02-08","commitResults":[{"hash":"0c57056fc83075f68dd5c3bec993cfac55ebecfb","messageTitle":"further cleanup and coding standard improvement","messageBody":"","fileTypesAndContributionMap":{"java":{"insertions":72,"deletions":79}}},{"hash":"30de721553d945d38bdd4b9c07ec94e6b7d7380b","messageTitle":"update main","messageBody":"","fileTypesAndContributionMap":{"java":{"insertions":1,"deletions":1}}},{"hash":"cdc1146b4d6c662b95691cc32d5665be6a058e3e","messageTitle":"Update packages","messageBody":"","fileTypesAndContributionMap":{"java":{"insertions":1,"deletions":1}}}]},{"date":"2023-02-13","commitResults":[{"hash":"41a601bf683f0b8b601ebfb6957faff2cb3046fb","messageTitle":"implemented delete feature","messageBody":"","tags":["A-Collections"],"fileTypesAndContributionMap":{"java":{"insertions":26,"deletions":4}}},{"hash":"f0aa5d60fe2ead501db23e121688cbabee8eebac","messageTitle":"implemented save and load feature","messageBody":"","fileTypesAndContributionMap":{"txt":{"insertions":4,"deletions":0},"java":{"insertions":143,"deletions":0}}},{"hash":"3f5a3a388715e49d99c6d13ce9c02e71de7c1979","messageTitle":"implemented level 6 and level 7","messageBody":"","tags":["Level-7","Level-6"],"fileTypesAndContributionMap":{"txt":{"insertions":3,"deletions":2},"java":{"insertions":3,"deletions":0}}},{"hash":"067d5bf1393e0bc8e755b884c1bb6e831bc735fd","messageTitle":"code cleaning and implement A-Jar","messageBody":"","tags":["A-Jar"],"fileTypesAndContributionMap":{"txt":{"insertions":1,"deletions":2},"java":{"insertions":6,"deletions":5}}}]},{"date":"2023-02-16","commitResults":[{"hash":"fd6b0432551ce206d77adebfc3011e8a85f471c0","messageTitle":"removed data folder","messageBody":"","fileTypesAndContributionMap":{"txt":{"insertions":0,"deletions":4}}}]},{"date":"2023-02-26","commitResults":[{"hash":"9d349a7b0a477376689e2b5778d5510d312c0906","messageTitle":"refactored code to use more OOP","messageBody":"","tags":["Level-8","A-MoreOOP"],"fileTypesAndContributionMap":{"java":{"insertions":145,"deletions":120}}},{"hash":"c3759af37eb585e404b77b920aef2b218ed2ae55","messageTitle":"Implemented minimal task for level 8","messageBody":"","fileTypesAndContributionMap":{"java":{"insertions":23,"deletions":8}}},{"hash":"7d6dd623844aff0a4c9268b8ec6ece9e3705d416","messageTitle":"Implemented Level-9","messageBody":"","fileTypesAndContributionMap":{"java":{"insertions":25,"deletions":5}}}]},{"date":"2023-02-27","commitResults":[{"hash":"bd64614d54a34f537b7114637e1d3f2da8e4e1cf","messageTitle":"did java documentation","messageBody":"","fileTypesAndContributionMap":{"java":{"insertions":244,"deletions":4}}}]},{"date":"2023-02-28","commitResults":[{"hash":"1dc100b2e5522a9cb79a57a836b0f9afca537aff","messageTitle":"updated readme.md","messageBody":"","tags":["A-UserGuide"],"fileTypesAndContributionMap":{"md":{"insertions":88,"deletions":14}}},{"hash":"0a5a8eccea477549515b13d018ef6fc83601bc63","messageTitle":"Add link to ip.jar","messageBody":"","fileTypesAndContributionMap":{"md":{"insertions":1,"deletions":1}}},{"hash":"1904c8073ca95980b5f6cabc7fc75c549182d295","messageTitle":"finalize readme","messageBody":"","tags":["A-Release"],"fileTypesAndContributionMap":{"md":{"insertions":10,"deletions":10}}}]}]},"authorFileTypeContributionMap":{"Rayleigh47":{"java":688,"md":88,"fxml":0,"sh":0,"bat":0,"gradle":0,"txt":6}},"authorContributionVariance":{"Rayleigh47":5139.992},"authorDisplayNameMap":{"Rayleigh47":"CS2113-T12-1 PANG..MING"}}
