[{"path":"src/main/java/Duke.java","fileType":"java","lines":[{"lineNumber":1,"author":{"gitId":"ong-ck"},"content":"import java.util.Scanner;","lastModifiedDate":"2023-01-26"},{"lineNumber":2,"author":{"gitId":"ong-ck"},"content":"","lastModifiedDate":"2023-01-26"},{"lineNumber":3,"author":{"gitId":"-"},"content":"public class Duke {","lastModifiedDate":"2019-07-29"},{"lineNumber":4,"author":{"gitId":"-"},"content":"    public static void main(String[] args) {","lastModifiedDate":"2019-07-29"},{"lineNumber":5,"author":{"gitId":"ong-ck"},"content":"        Scanner inputScanner \u003d new Scanner(System.in);","lastModifiedDate":"2023-01-26"},{"lineNumber":6,"author":{"gitId":"ong-ck"},"content":"        String userInput;","lastModifiedDate":"2023-01-26"},{"lineNumber":7,"author":{"gitId":"ong-ck"},"content":"        String[] userInputs;","lastModifiedDate":"2023-01-26"},{"lineNumber":8,"author":{"gitId":"ong-ck"},"content":"","lastModifiedDate":"2023-01-26"},{"lineNumber":9,"author":{"gitId":"ong-ck"},"content":"        // Greeting the user","lastModifiedDate":"2023-01-26"},{"lineNumber":10,"author":{"gitId":"ong-ck"},"content":"        Messages.hello();","lastModifiedDate":"2023-01-26"},{"lineNumber":11,"author":{"gitId":"ong-ck"},"content":"        ","lastModifiedDate":"2023-01-26"},{"lineNumber":12,"author":{"gitId":"ong-ck"},"content":"        do {","lastModifiedDate":"2023-01-26"},{"lineNumber":13,"author":{"gitId":"ong-ck"},"content":"            userInput \u003d inputScanner.nextLine();","lastModifiedDate":"2023-01-26"},{"lineNumber":14,"author":{"gitId":"ong-ck"},"content":"            userInputs \u003d userInput.split(\" \", 0);","lastModifiedDate":"2023-01-26"},{"lineNumber":15,"author":{"gitId":"ong-ck"},"content":"            switch(userInputs[0]) {","lastModifiedDate":"2023-01-26"},{"lineNumber":16,"author":{"gitId":"ong-ck"},"content":"            case \"list\":","lastModifiedDate":"2023-01-26"},{"lineNumber":17,"author":{"gitId":"ong-ck"},"content":"                Lists.printList();","lastModifiedDate":"2023-01-26"},{"lineNumber":18,"author":{"gitId":"ong-ck"},"content":"                break;","lastModifiedDate":"2023-01-26"},{"lineNumber":19,"author":{"gitId":"ong-ck"},"content":"            case \"mark\":","lastModifiedDate":"2023-01-26"},{"lineNumber":20,"author":{"gitId":"ong-ck"},"content":"                Lists.markDone(Integer.parseInt(userInputs[1]));","lastModifiedDate":"2023-01-26"},{"lineNumber":21,"author":{"gitId":"ong-ck"},"content":"                break;","lastModifiedDate":"2023-01-26"},{"lineNumber":22,"author":{"gitId":"ong-ck"},"content":"            case \"unmark\":","lastModifiedDate":"2023-01-26"},{"lineNumber":23,"author":{"gitId":"ong-ck"},"content":"                Lists.markUndone(Integer.parseInt(userInputs[1]));","lastModifiedDate":"2023-01-26"},{"lineNumber":24,"author":{"gitId":"ong-ck"},"content":"                break;","lastModifiedDate":"2023-01-26"},{"lineNumber":25,"author":{"gitId":"ong-ck"},"content":"            default:","lastModifiedDate":"2023-01-26"},{"lineNumber":26,"author":{"gitId":"ong-ck"},"content":"                Lists.addItem(userInput);","lastModifiedDate":"2023-01-26"},{"lineNumber":27,"author":{"gitId":"ong-ck"},"content":"            }","lastModifiedDate":"2023-01-26"},{"lineNumber":28,"author":{"gitId":"ong-ck"},"content":"        } while (!(userInput.equals(\"bye\")));","lastModifiedDate":"2023-01-26"},{"lineNumber":29,"author":{"gitId":"ong-ck"},"content":"","lastModifiedDate":"2023-01-26"},{"lineNumber":30,"author":{"gitId":"ong-ck"},"content":"        Messages.bye();","lastModifiedDate":"2023-01-26"},{"lineNumber":31,"author":{"gitId":"ong-ck"},"content":"        Messages.line();","lastModifiedDate":"2023-01-26"},{"lineNumber":32,"author":{"gitId":"-"},"content":"    }","lastModifiedDate":"2019-07-29"},{"lineNumber":33,"author":{"gitId":"-"},"content":"}","lastModifiedDate":"2019-07-29"}],"authorContributionMap":{"ong-ck":29,"-":4}},{"path":"src/main/java/Lists.java","fileType":"java","lines":[{"lineNumber":1,"author":{"gitId":"ong-ck"},"content":"import java.util.ArrayList;","lastModifiedDate":"2023-01-26"},{"lineNumber":2,"author":{"gitId":"ong-ck"},"content":"","lastModifiedDate":"2023-01-26"},{"lineNumber":3,"author":{"gitId":"ong-ck"},"content":"public class Lists {","lastModifiedDate":"2023-01-26"},{"lineNumber":4,"author":{"gitId":"ong-ck"},"content":"    private static ArrayList\u003cTask\u003e list \u003d new ArrayList\u003cTask\u003e();","lastModifiedDate":"2023-01-26"},{"lineNumber":5,"author":{"gitId":"ong-ck"},"content":"","lastModifiedDate":"2023-01-26"},{"lineNumber":6,"author":{"gitId":"ong-ck"},"content":"    public static void addItem(String item) {","lastModifiedDate":"2023-01-26"},{"lineNumber":7,"author":{"gitId":"ong-ck"},"content":"        Task task \u003d new Task(item);","lastModifiedDate":"2023-01-26"},{"lineNumber":8,"author":{"gitId":"ong-ck"},"content":"        list.add(task);","lastModifiedDate":"2023-01-26"},{"lineNumber":9,"author":{"gitId":"ong-ck"},"content":"        Messages.line();","lastModifiedDate":"2023-01-26"},{"lineNumber":10,"author":{"gitId":"ong-ck"},"content":"        System.out.println(\"Added: \" + item);","lastModifiedDate":"2023-01-26"},{"lineNumber":11,"author":{"gitId":"ong-ck"},"content":"        Messages.line();","lastModifiedDate":"2023-01-26"},{"lineNumber":12,"author":{"gitId":"ong-ck"},"content":"    }","lastModifiedDate":"2023-01-26"},{"lineNumber":13,"author":{"gitId":"ong-ck"},"content":"","lastModifiedDate":"2023-01-26"},{"lineNumber":14,"author":{"gitId":"ong-ck"},"content":"    public static void printList() {","lastModifiedDate":"2023-01-26"},{"lineNumber":15,"author":{"gitId":"ong-ck"},"content":"        Messages.line();","lastModifiedDate":"2023-01-26"},{"lineNumber":16,"author":{"gitId":"ong-ck"},"content":"        System.out.println(\"Here are the tasks in your list:\");","lastModifiedDate":"2023-01-26"},{"lineNumber":17,"author":{"gitId":"ong-ck"},"content":"        for (int i \u003d 0; i \u003c list.size(); i++) {","lastModifiedDate":"2023-01-26"},{"lineNumber":18,"author":{"gitId":"ong-ck"},"content":"            System.out.println(Integer.toString(i + 1) + \".[\" + list.get(i).getStatusIcon() + \"] \" + list.get(i).description);","lastModifiedDate":"2023-01-26"},{"lineNumber":19,"author":{"gitId":"ong-ck"},"content":"        }","lastModifiedDate":"2023-01-26"},{"lineNumber":20,"author":{"gitId":"ong-ck"},"content":"        Messages.line();","lastModifiedDate":"2023-01-26"},{"lineNumber":21,"author":{"gitId":"ong-ck"},"content":"    }","lastModifiedDate":"2023-01-26"},{"lineNumber":22,"author":{"gitId":"ong-ck"},"content":"","lastModifiedDate":"2023-01-26"},{"lineNumber":23,"author":{"gitId":"ong-ck"},"content":"    public static void markDone(int index) {","lastModifiedDate":"2023-01-26"},{"lineNumber":24,"author":{"gitId":"ong-ck"},"content":"        list.get(index - 1).isDone \u003d true;","lastModifiedDate":"2023-01-26"},{"lineNumber":25,"author":{"gitId":"ong-ck"},"content":"        Messages.line();","lastModifiedDate":"2023-01-26"},{"lineNumber":26,"author":{"gitId":"ong-ck"},"content":"        System.out.println(\"Nice! I\u0027ve marked this task as done:\");","lastModifiedDate":"2023-01-26"},{"lineNumber":27,"author":{"gitId":"ong-ck"},"content":"        System.out.println(\"  [\" + list.get(index - 1).getStatusIcon() + \"] \" + list.get(index - 1).description);","lastModifiedDate":"2023-01-26"},{"lineNumber":28,"author":{"gitId":"ong-ck"},"content":"        Messages.line();","lastModifiedDate":"2023-01-26"},{"lineNumber":29,"author":{"gitId":"ong-ck"},"content":"    }","lastModifiedDate":"2023-01-26"},{"lineNumber":30,"author":{"gitId":"ong-ck"},"content":"","lastModifiedDate":"2023-01-26"},{"lineNumber":31,"author":{"gitId":"ong-ck"},"content":"    public static void markUndone(int index) {","lastModifiedDate":"2023-01-26"},{"lineNumber":32,"author":{"gitId":"ong-ck"},"content":"        list.get(index - 1).isDone \u003d false;","lastModifiedDate":"2023-01-26"},{"lineNumber":33,"author":{"gitId":"ong-ck"},"content":"        Messages.line();","lastModifiedDate":"2023-01-26"},{"lineNumber":34,"author":{"gitId":"ong-ck"},"content":"        System.out.println(\"OK, I\u0027ve marked this task as not done yet:\");","lastModifiedDate":"2023-01-26"},{"lineNumber":35,"author":{"gitId":"ong-ck"},"content":"        System.out.println(\"  [\" + list.get(index - 1).getStatusIcon() + \"] \" + list.get(index - 1).description);","lastModifiedDate":"2023-01-26"},{"lineNumber":36,"author":{"gitId":"ong-ck"},"content":"        Messages.line();","lastModifiedDate":"2023-01-26"},{"lineNumber":37,"author":{"gitId":"ong-ck"},"content":"    }","lastModifiedDate":"2023-01-26"},{"lineNumber":38,"author":{"gitId":"ong-ck"},"content":"}","lastModifiedDate":"2023-01-26"}],"authorContributionMap":{"ong-ck":38}},{"path":"src/main/java/Messages.java","fileType":"java","lines":[{"lineNumber":1,"author":{"gitId":"ong-ck"},"content":"public class Messages {","lastModifiedDate":"2023-01-26"},{"lineNumber":2,"author":{"gitId":"ong-ck"},"content":"","lastModifiedDate":"2023-01-26"},{"lineNumber":3,"author":{"gitId":"ong-ck"},"content":"    public static void logo() {","lastModifiedDate":"2023-01-26"},{"lineNumber":4,"author":{"gitId":"ong-ck"},"content":"        String logo \u003d \" ____        _        \\n\"","lastModifiedDate":"2023-01-26"},{"lineNumber":5,"author":{"gitId":"ong-ck"},"content":"                + \"|  _ \\\\ _   _| | _____ \\n\"","lastModifiedDate":"2023-01-26"},{"lineNumber":6,"author":{"gitId":"ong-ck"},"content":"                + \"| | | | | | | |/ / _ \\\\\\n\"","lastModifiedDate":"2023-01-26"},{"lineNumber":7,"author":{"gitId":"ong-ck"},"content":"                + \"| |_| | |_| |   \u003c  __/\\n\"","lastModifiedDate":"2023-01-26"},{"lineNumber":8,"author":{"gitId":"ong-ck"},"content":"                + \"|____/ \\\\__,_|_|\\\\_\\\\___|\\n\";","lastModifiedDate":"2023-01-26"},{"lineNumber":9,"author":{"gitId":"ong-ck"},"content":"","lastModifiedDate":"2023-01-26"},{"lineNumber":10,"author":{"gitId":"ong-ck"},"content":"        System.out.println(logo + \"\\n\");","lastModifiedDate":"2023-01-26"},{"lineNumber":11,"author":{"gitId":"ong-ck"},"content":"    }","lastModifiedDate":"2023-01-26"},{"lineNumber":12,"author":{"gitId":"ong-ck"},"content":"","lastModifiedDate":"2023-01-26"},{"lineNumber":13,"author":{"gitId":"ong-ck"},"content":"    public static void line() {","lastModifiedDate":"2023-01-26"},{"lineNumber":14,"author":{"gitId":"ong-ck"},"content":"        System.out.println(\"____________________________________________________________\");","lastModifiedDate":"2023-01-26"},{"lineNumber":15,"author":{"gitId":"ong-ck"},"content":"    }","lastModifiedDate":"2023-01-26"},{"lineNumber":16,"author":{"gitId":"ong-ck"},"content":"","lastModifiedDate":"2023-01-26"},{"lineNumber":17,"author":{"gitId":"ong-ck"},"content":"    public static void hello() {","lastModifiedDate":"2023-01-26"},{"lineNumber":18,"author":{"gitId":"ong-ck"},"content":"        Messages.line();","lastModifiedDate":"2023-01-26"},{"lineNumber":19,"author":{"gitId":"ong-ck"},"content":"        Messages.logo();","lastModifiedDate":"2023-01-26"},{"lineNumber":20,"author":{"gitId":"ong-ck"},"content":"        System.out.println(\"Hello! I\u0027m Duke\\nWhat can I do for you?\");","lastModifiedDate":"2023-01-26"},{"lineNumber":21,"author":{"gitId":"ong-ck"},"content":"        Messages.line();","lastModifiedDate":"2023-01-26"},{"lineNumber":22,"author":{"gitId":"ong-ck"},"content":"    }","lastModifiedDate":"2023-01-26"},{"lineNumber":23,"author":{"gitId":"ong-ck"},"content":"","lastModifiedDate":"2023-01-26"},{"lineNumber":24,"author":{"gitId":"ong-ck"},"content":"    public static void bye() {","lastModifiedDate":"2023-01-26"},{"lineNumber":25,"author":{"gitId":"ong-ck"},"content":"        System.out.println(\"Bye. Hope to see you again soon!\");","lastModifiedDate":"2023-01-26"},{"lineNumber":26,"author":{"gitId":"ong-ck"},"content":"    }","lastModifiedDate":"2023-01-26"},{"lineNumber":27,"author":{"gitId":"ong-ck"},"content":"","lastModifiedDate":"2023-01-26"},{"lineNumber":28,"author":{"gitId":"ong-ck"},"content":"    public static void echo(String userInput) {","lastModifiedDate":"2023-01-26"},{"lineNumber":29,"author":{"gitId":"ong-ck"},"content":"        Messages.line();","lastModifiedDate":"2023-01-26"},{"lineNumber":30,"author":{"gitId":"ong-ck"},"content":"        System.out.println(userInput);","lastModifiedDate":"2023-01-26"},{"lineNumber":31,"author":{"gitId":"ong-ck"},"content":"        Messages.line();","lastModifiedDate":"2023-01-26"},{"lineNumber":32,"author":{"gitId":"ong-ck"},"content":"    }","lastModifiedDate":"2023-01-26"},{"lineNumber":33,"author":{"gitId":"ong-ck"},"content":"}","lastModifiedDate":"2023-01-26"}],"authorContributionMap":{"ong-ck":33}},{"path":"src/main/java/Task.java","fileType":"java","lines":[{"lineNumber":1,"author":{"gitId":"ong-ck"},"content":"public class Task {","lastModifiedDate":"2023-01-26"},{"lineNumber":2,"author":{"gitId":"ong-ck"},"content":"    protected String description;","lastModifiedDate":"2023-01-26"},{"lineNumber":3,"author":{"gitId":"ong-ck"},"content":"    protected boolean isDone;","lastModifiedDate":"2023-01-26"},{"lineNumber":4,"author":{"gitId":"ong-ck"},"content":"","lastModifiedDate":"2023-01-26"},{"lineNumber":5,"author":{"gitId":"ong-ck"},"content":"    public Task(String description) {","lastModifiedDate":"2023-01-26"},{"lineNumber":6,"author":{"gitId":"ong-ck"},"content":"        this.description \u003d description;","lastModifiedDate":"2023-01-26"},{"lineNumber":7,"author":{"gitId":"ong-ck"},"content":"        this.isDone \u003d false;","lastModifiedDate":"2023-01-26"},{"lineNumber":8,"author":{"gitId":"ong-ck"},"content":"    }","lastModifiedDate":"2023-01-26"},{"lineNumber":9,"author":{"gitId":"ong-ck"},"content":"","lastModifiedDate":"2023-01-26"},{"lineNumber":10,"author":{"gitId":"ong-ck"},"content":"    public String getStatusIcon() {","lastModifiedDate":"2023-01-26"},{"lineNumber":11,"author":{"gitId":"ong-ck"},"content":"        return (isDone ? \"X\" : \" \"); // mark done task with X","lastModifiedDate":"2023-01-26"},{"lineNumber":12,"author":{"gitId":"ong-ck"},"content":"    }","lastModifiedDate":"2023-01-26"},{"lineNumber":13,"author":{"gitId":"ong-ck"},"content":"}","lastModifiedDate":"2023-01-26"}],"authorContributionMap":{"ong-ck":13}}]
